<?xml version="1.0" encoding="ISO-8859-1"?>
<LxERP>
    <Firm>
        <CodeTables>
               <!--  CodeSLSchedule must be explicitly created and listed before used -->
                 
        	       <!--  CodeSLSchedule must be explicitly created and listed before used -->
        	        <CodeSLSchedule clientID="sched_baserent">
        	    	<ShortName>Base Rent SL</ShortName>
        	        			</CodeSLSchedule>
        	        			<CodeExpenseType clientID="etype_baserent">
        	    			<ShortName>Rent</ShortName>
        	    			<ParentCodeExpenseGroupID>Base Rent</ParentCodeExpenseGroupID>
        	    			<CodeSLScheduleID>Base Rent SL</CodeSLScheduleID>
        	        		</CodeExpenseType>
        </CodeTables>
        <Contracts>
            <Contract>
                <AutomaticRenewalInLease>false</AutomaticRenewalInLease>
                <AutomaticRenewalOption>false</AutomaticRenewalOption>
                <BargainRenewalInLease>false</BargainRenewalInLease>
                <BargainRenewalOption>false</BargainRenewalOption>
                <ClientEntityID>Contract-AMPERPERIOD10</ClientEntityID>
                <CodeBuildingAreaUnitID>Square Feet</CodeBuildingAreaUnitID>
                <CodeContractCategoryID>Leased</CodeContractCategoryID>
                <CodeContractGroupID>Lease</CodeContractGroupID>
                <CodeContractTypeID>Option</CodeContractTypeID>
                <CommenceDate>2010-01-01</CommenceDate>
                <ContainsBargainPurchaseOption>false</ContainsBargainPurchaseOption>
                <ContractName>Straight Line Amortize Pro-rate Per Period Contract</ContractName>
                <DoesTitleRevertToTenant>false</DoesTitleRevertToTenant>
                <ExecuteDate>2010-01-01</ExecuteDate>
                <ExpireDate>2020-12-31</ExpireDate>
                <LocationID clientID="lucernex-location">Lucernex-Project</LocationID>
                <MonthToMonth>false</MonthToMonth>
                <PaymentsBeginDate>2010-01-01</PaymentsBeginDate>
                <PaymentsEndDate>2020-12-31</PaymentsEndDate>
                <PossessionBeginDate>2010-01-01</PossessionBeginDate>
                <ProgramID clientID="client-UNI5190">Fiscal Calendar Portfolio</ProgramID>
                <ProjectEntityID clientID="client-SL-618">Straight Line Amortize Pro-rate Per Period Contract</ProjectEntityID>
                <RentableArea>0.00</RentableArea>
                <ExpenseSetup clientID="client-788635">
                    <ApplyTax1Flag>false</ApplyTax1Flag>
                    <ApplyTax2Flag>false</ApplyTax2Flag>
                    <ApplyTax3Flag>false</ApplyTax3Flag>
                    <CodeBuildingAreaUnitID>Square Feet</CodeBuildingAreaUnitID>
                    <CodeExpenseGroupID>Base Rent</CodeExpenseGroupID>
                    <CodeExpenseTypeID clientID="client-14676">Rent</CodeExpenseTypeID>
                    <CodeFrequencyID>Annually</CodeFrequencyID>
                    <HoldFlag>false</HoldFlag>
                    <IsReceivable>false</IsReceivable>
                    <ProjectEntityID>SL-618</ProjectEntityID>
                    <ReadyForPaymentFlag>false</ReadyForPaymentFlag>
                    <ReconcilableExpense>false</ReconcilableExpense>
                    <TaxesIncludedFlag>false</TaxesIncludedFlag>
                   <ExpenseSchedule>
                        <AnnualAmount>100000.00000</AnnualAmount>
                        <BeginDate>2014-01-01</BeginDate>
                        <CodeApprovalStatusID>Review</CodeApprovalStatusID>
                        <EndDate>2017-12-31</EndDate>
                        <FirstPaymentAmount>100000.00000</FirstPaymentAmount>
                        <HoldFlag>false</HoldFlag>
                        <LastPaymentAmount>100000.00000</LastPaymentAmount>
                        <OptionRentFlag>false</OptionRentFlag>
                        <PaymentAmount>100000.00000</PaymentAmount>
                        <ProcessedFlag>false</ProcessedFlag>
                        <ProjectEntityID>SL-618</ProjectEntityID>
                        <ReadyForPaymentFlag>false</ReadyForPaymentFlag>
                    </ExpenseSchedule>                    
                </ExpenseSetup>
            </Contract>
        </Contracts>
    </Firm>
</LxERP>
