<?xml version="1.0" encoding="UTF-8"?>
<mes:LxERP xmlns:mes="http://iwms.lucernex.com/messaging">
    <mes:Firm Name="Selenium-B1.199">
        <mes:PageLayouts>
            <mes:PageLayout>
                <mes:ClientID>lucernex-db01_IWMS_Production_SAN_20100429_094012910_2475</mes:ClientID>
                <mes:PageLayoutName>Management</mes:PageLayoutName>
                <mes:Details>
                    <mes:AllowUserCreate>false</mes:AllowUserCreate>
                    <mes:AllowEdit>true</mes:AllowEdit>
                    <mes:IsGlobalReport>true</mes:IsGlobalReport>
                    <mes:OutputType>L</mes:OutputType>
                    <mes:PageLayoutType>V</mes:PageLayoutType>
                    <mes:PreviousPageLayoutID ClientID="lucernex-db01_IWMS_Production_SAN_20100429_094012878_2472">Comments</mes:PreviousPageLayoutID>
                    <mes:PrimaryCodeSQLTableID>ProjectEntity</mes:PrimaryCodeSQLTableID>
                    <mes:EntitySelectionFilter>31</mes:EntitySelectionFilter>
                    <mes:RunModeFilters>0</mes:RunModeFilters>
                </mes:Details>
                <mes:PageLayoutFields>
                    <mes:PageLayoutField>
                        <mes:ClientID>lucernex-db01_IWMS_Production_SAN_20100429_094013488_631170</mes:ClientID>
                        <mes:PageLayoutID ClientID="lucernex-db01_IWMS_Production_SAN_20100429_094012910_2475">Management</mes:PageLayoutID>
                        <mes:ReportGroupAvailableFieldID ClientID="ERP_1332">ManagerIDList</mes:ReportGroupAvailableFieldID>
                        <mes:Details>
                            <mes:DisplayLabel>Project Managers</mes:DisplayLabel>
                            <mes:DisplayOption1>0</mes:DisplayOption1>
                            <mes:DisplayOption2>0</mes:DisplayOption2>
                            <mes:HeaderColumnPosition>-1</mes:HeaderColumnPosition>
                            <mes:ViewColumnPosition>-1</mes:ViewColumnPosition>
                            <mes:ViewRowPosition>-1</mes:ViewRowPosition>
                            <mes:ViewFieldWidth>1</mes:ViewFieldWidth>
                            <mes:ViewFieldHeight>1</mes:ViewFieldHeight>
                            <mes:EditColumnPosition>1</mes:EditColumnPosition>
                            <mes:EditRowPosition>1</mes:EditRowPosition>
                            <mes:EditFieldWidth>1</mes:EditFieldWidth>
                            <mes:EditFieldHeight>1</mes:EditFieldHeight>
                            <mes:JSONConfigText>{}</mes:JSONConfigText>
                        </mes:Details>
                    </mes:PageLayoutField>
                </mes:PageLayoutFields>
                <mes:PageLayoutFilters/>
            </mes:PageLayout>
            <mes:PageLayout>
                <mes:ClientID>SQL153/SQL_TEST_TestB_20160727_20161011_141529253_44642</mes:ClientID>
                <mes:PageLayoutName>Build Sequence Number Page Layout</mes:PageLayoutName>
                <mes:Details>
                    <mes:AllowEdit>true</mes:AllowEdit>
                    <mes:IsGlobalReport>true</mes:IsGlobalReport>
                    <mes:OutputType>L</mes:OutputType>
                    <mes:PageLayoutType>V</mes:PageLayoutType>
                    <mes:ParentPageLayoutID ClientID="20">Summary</mes:ParentPageLayoutID>
                    <mes:PrimaryCodeSQLTableID>Project</mes:PrimaryCodeSQLTableID>
                    <mes:FirmID>Selenium-B1.199</mes:FirmID>
                    <mes:EntitySelectionFilter>31</mes:EntitySelectionFilter>
                    <mes:RunModeFilters>0</mes:RunModeFilters>
                </mes:Details>
                <mes:PageLayoutFields>
                    <mes:PageLayoutField>
                        <mes:ClientID>SQL153/SQL_TEST_TestB_20160727_20161011_141529366_1474206</mes:ClientID>
                        <mes:PageLayoutID ClientID="SQL153/SQL_TEST_TestB_20160727_20161011_141529253_44642">Build Sequence Number Page Layout</mes:PageLayoutID>
                        <mes:ReportGroupAvailableFieldID ClientID="ERP_510">StaticText</mes:ReportGroupAvailableFieldID>
                        <mes:Details>
                            <mes:FirmID>Selenium-B1.199</mes:FirmID>
                            <mes:StaticText>General Information</mes:StaticText>
                            <mes:DisplayLabel>General Information</mes:DisplayLabel>
                            <mes:DisplayOption1>0</mes:DisplayOption1>
                            <mes:DisplayOption2>268435744</mes:DisplayOption2>
                            <mes:HeaderColumnPosition>-1</mes:HeaderColumnPosition>
                            <mes:ViewColumnPosition>-1</mes:ViewColumnPosition>
                            <mes:ViewRowPosition>-1</mes:ViewRowPosition>
                            <mes:ViewFieldWidth>1</mes:ViewFieldWidth>
                            <mes:ViewFieldHeight>1</mes:ViewFieldHeight>
                            <mes:EditColumnPosition>1</mes:EditColumnPosition>
                            <mes:EditRowPosition>1</mes:EditRowPosition>
                            <mes:EditFieldWidth>5</mes:EditFieldWidth>
                            <mes:EditFieldHeight>1</mes:EditFieldHeight>
                            <mes:JSONConfigText>{}</mes:JSONConfigText>
                        </mes:Details>
                    </mes:PageLayoutField>
                    <mes:PageLayoutField>
                        <mes:ClientID>SQL153/SQL_TEST_TestB_20160727_20161011_141529424_1474207</mes:ClientID>
                        <mes:PageLayoutID ClientID="SQL153/SQL_TEST_TestB_20160727_20161011_141529253_44642">Build Sequence Number Page Layout</mes:PageLayoutID>
                        <mes:ReportGroupAvailableFieldID ClientID="ERP_510">StaticText</mes:ReportGroupAvailableFieldID>
                        <mes:Details>
                            <mes:FirmID>Selenium-B1.199</mes:FirmID>
                            <mes:StaticText>Management</mes:StaticText>
                            <mes:DisplayLabel>Management</mes:DisplayLabel>
                            <mes:DisplayOption1>0</mes:DisplayOption1>
                            <mes:DisplayOption2>268435744</mes:DisplayOption2>
                            <mes:HeaderColumnPosition>-1</mes:HeaderColumnPosition>
                            <mes:ViewColumnPosition>-1</mes:ViewColumnPosition>
                            <mes:ViewRowPosition>-1</mes:ViewRowPosition>
                            <mes:ViewFieldWidth>1</mes:ViewFieldWidth>
                            <mes:ViewFieldHeight>1</mes:ViewFieldHeight>
                            <mes:EditColumnPosition>6</mes:EditColumnPosition>
                            <mes:EditRowPosition>1</mes:EditRowPosition>
                            <mes:EditFieldWidth>6</mes:EditFieldWidth>
                            <mes:EditFieldHeight>1</mes:EditFieldHeight>
                            <mes:JSONConfigText>{}</mes:JSONConfigText>
                        </mes:Details>
                    </mes:PageLayoutField>
                    <mes:PageLayoutField>
                        <mes:ClientID>SQL153/SQL_TEST_TestB_20160727_20161011_141529443_1474208</mes:ClientID>
                        <mes:PageLayoutID ClientID="SQL153/SQL_TEST_TestB_20160727_20161011_141529253_44642">Build Sequence Number Page Layout</mes:PageLayoutID>
                        <mes:ReportGroupAvailableFieldID ClientID="ERP_1320">EntityPhoto</mes:ReportGroupAvailableFieldID>
                        <mes:Details>
                            <mes:FirmID>Selenium-B1.199</mes:FirmID>
                            <mes:DisplayLabel>Entity Photo</mes:DisplayLabel>
                            <mes:DisplayOption1>67109120</mes:DisplayOption1>
                            <mes:DisplayOption2>0</mes:DisplayOption2>
                            <mes:HeaderColumnPosition>-1</mes:HeaderColumnPosition>
                            <mes:ViewColumnPosition>-1</mes:ViewColumnPosition>
                            <mes:ViewRowPosition>-1</mes:ViewRowPosition>
                            <mes:ViewFieldWidth>1</mes:ViewFieldWidth>
                            <mes:ViewFieldHeight>1</mes:ViewFieldHeight>
                            <mes:EditColumnPosition>1</mes:EditColumnPosition>
                            <mes:EditRowPosition>3</mes:EditRowPosition>
                            <mes:EditFieldWidth>5</mes:EditFieldWidth>
                            <mes:EditFieldHeight>6</mes:EditFieldHeight>
                            <mes:JSONConfigText>{}</mes:JSONConfigText>
                        </mes:Details>
                    </mes:PageLayoutField>
                    <mes:PageLayoutField>
                        <mes:ClientID>SQL153/SQL_TEST_TestB_20160727_20161011_141529460_1474209</mes:ClientID>
                        <mes:PageLayoutID ClientID="SQL153/SQL_TEST_TestB_20160727_20161011_141529253_44642">Build Sequence Number Page Layout</mes:PageLayoutID>
                        <mes:ReportGroupAvailableFieldID ClientID="ERP_509">BlankSpace</mes:ReportGroupAvailableFieldID>
                        <mes:Details>
                            <mes:FirmID>Selenium-B1.199</mes:FirmID>
                            <mes:DisplayLabel>Blank Space</mes:DisplayLabel>
                            <mes:DisplayOption1>0</mes:DisplayOption1>
                            <mes:DisplayOption2>0</mes:DisplayOption2>
                            <mes:HeaderColumnPosition>-1</mes:HeaderColumnPosition>
                            <mes:ViewColumnPosition>-1</mes:ViewColumnPosition>
                            <mes:ViewRowPosition>-1</mes:ViewRowPosition>
                            <mes:ViewFieldWidth>1</mes:ViewFieldWidth>
                            <mes:ViewFieldHeight>1</mes:ViewFieldHeight>
                            <mes:EditColumnPosition>1</mes:EditColumnPosition>
                            <mes:EditRowPosition>2</mes:EditRowPosition>
                            <mes:EditFieldWidth>5</mes:EditFieldWidth>
                            <mes:EditFieldHeight>1</mes:EditFieldHeight>
                            <mes:JSONConfigText>{}</mes:JSONConfigText>
                        </mes:Details>
                    </mes:PageLayoutField>
                    <mes:PageLayoutField>
                        <mes:ClientID>SQL153/SQL_TEST_TestB_20160727_20161011_141529478_1474210</mes:ClientID>
                        <mes:PageLayoutID ClientID="SQL153/SQL_TEST_TestB_20160727_20161011_141529253_44642">Build Sequence Number Page Layout</mes:PageLayoutID>
                        <mes:ReportGroupAvailableFieldID ClientID="ERP_437">ProgramName</mes:ReportGroupAvailableFieldID>
                        <mes:Details>
                            <mes:FirmID>Selenium-B1.199</mes:FirmID>
                            <mes:DisplayLabel>Name</mes:DisplayLabel>
                            <mes:DisplayOption1>33554440</mes:DisplayOption1>
                            <mes:DisplayOption2>0</mes:DisplayOption2>
                            <mes:HeaderColumnPosition>-1</mes:HeaderColumnPosition>
                            <mes:ViewColumnPosition>-1</mes:ViewColumnPosition>
                            <mes:ViewRowPosition>-1</mes:ViewRowPosition>
                            <mes:ViewFieldWidth>1</mes:ViewFieldWidth>
                            <mes:ViewFieldHeight>1</mes:ViewFieldHeight>
                            <mes:EditColumnPosition>1</mes:EditColumnPosition>
                            <mes:EditRowPosition>10</mes:EditRowPosition>
                            <mes:EditFieldWidth>5</mes:EditFieldWidth>
                            <mes:EditFieldHeight>1</mes:EditFieldHeight>
                            <mes:JSONConfigText>{}</mes:JSONConfigText>
                        </mes:Details>
                    </mes:PageLayoutField>
                    <mes:PageLayoutField>
                        <mes:ClientID>SQL153/SQL_TEST_TestB_20160727_20161011_141529495_1474211</mes:ClientID>
                        <mes:PageLayoutID ClientID="SQL153/SQL_TEST_TestB_20160727_20161011_141529253_44642">Build Sequence Number Page Layout</mes:PageLayoutID>
                        <mes:ReportGroupAvailableFieldID ClientID="ERP_510">StaticText</mes:ReportGroupAvailableFieldID>
                        <mes:Details>
                            <mes:FirmID>Selenium-B1.199</mes:FirmID>
                            <mes:StaticText>Projects Summary</mes:StaticText>
                            <mes:DisplayLabel>Projects Summary</mes:DisplayLabel>
                            <mes:DisplayOption1>0</mes:DisplayOption1>
                            <mes:DisplayOption2>268435744</mes:DisplayOption2>
                            <mes:HeaderColumnPosition>-1</mes:HeaderColumnPosition>
                            <mes:ViewColumnPosition>-1</mes:ViewColumnPosition>
                            <mes:ViewRowPosition>-1</mes:ViewRowPosition>
                            <mes:ViewFieldWidth>1</mes:ViewFieldWidth>
                            <mes:ViewFieldHeight>1</mes:ViewFieldHeight>
                            <mes:EditColumnPosition>1</mes:EditColumnPosition>
                            <mes:EditRowPosition>13</mes:EditRowPosition>
                            <mes:EditFieldWidth>5</mes:EditFieldWidth>
                            <mes:EditFieldHeight>1</mes:EditFieldHeight>
                            <mes:JSONConfigText>{}</mes:JSONConfigText>
                        </mes:Details>
                    </mes:PageLayoutField>
                    <mes:PageLayoutField>
                        <mes:ClientID>SQL153/SQL_TEST_TestB_20160727_20161011_141529512_1474212</mes:ClientID>
                        <mes:PageLayoutID ClientID="SQL153/SQL_TEST_TestB_20160727_20161011_141529253_44642">Build Sequence Number Page Layout</mes:PageLayoutID>
                        <mes:ReportGroupAvailableFieldID ClientID="ERP_1314">SubEditForm</mes:ReportGroupAvailableFieldID>
                        <mes:Details>
                            <mes:FirmID>Selenium-B1.199</mes:FirmID>
                            <mes:SubPageLayoutID ClientID="lucernex-db01_IWMS_Production_SAN_20100429_094012910_2475">Management</mes:SubPageLayoutID>
                            <mes:DisplayLabel>Sub Edit Form</mes:DisplayLabel>
                            <mes:DisplayOption1>4864</mes:DisplayOption1>
                            <mes:DisplayOption2>0</mes:DisplayOption2>
                            <mes:HeaderColumnPosition>-1</mes:HeaderColumnPosition>
                            <mes:ViewColumnPosition>-1</mes:ViewColumnPosition>
                            <mes:ViewRowPosition>-1</mes:ViewRowPosition>
                            <mes:ViewFieldWidth>1</mes:ViewFieldWidth>
                            <mes:ViewFieldHeight>1</mes:ViewFieldHeight>
                            <mes:EditColumnPosition>6</mes:EditColumnPosition>
                            <mes:EditRowPosition>2</mes:EditRowPosition>
                            <mes:EditFieldWidth>6</mes:EditFieldWidth>
                            <mes:EditFieldHeight>1</mes:EditFieldHeight>
                            <mes:JSONConfigText>{}</mes:JSONConfigText>
                        </mes:Details>
                    </mes:PageLayoutField>
                    <mes:PageLayoutField>
                        <mes:ClientID>SQL153/SQL_TEST_TestB_20160727_20161011_141529528_1474213</mes:ClientID>
                        <mes:PageLayoutID ClientID="SQL153/SQL_TEST_TestB_20160727_20161011_141529253_44642">Build Sequence Number Page Layout</mes:PageLayoutID>
                        <mes:ReportGroupAvailableFieldID ClientID="ERP_510">StaticText</mes:ReportGroupAvailableFieldID>
                        <mes:Details>
                            <mes:FirmID>Selenium-B1.199</mes:FirmID>
                            <mes:StaticText>Program Counts</mes:StaticText>
                            <mes:DisplayLabel>Program Counts</mes:DisplayLabel>
                            <mes:DisplayOption1>0</mes:DisplayOption1>
                            <mes:DisplayOption2>268435744</mes:DisplayOption2>
                            <mes:HeaderColumnPosition>-1</mes:HeaderColumnPosition>
                            <mes:ViewColumnPosition>-1</mes:ViewColumnPosition>
                            <mes:ViewRowPosition>-1</mes:ViewRowPosition>
                            <mes:ViewFieldWidth>1</mes:ViewFieldWidth>
                            <mes:ViewFieldHeight>1</mes:ViewFieldHeight>
                            <mes:EditColumnPosition>6</mes:EditColumnPosition>
                            <mes:EditRowPosition>4</mes:EditRowPosition>
                            <mes:EditFieldWidth>6</mes:EditFieldWidth>
                            <mes:EditFieldHeight>1</mes:EditFieldHeight>
                            <mes:JSONConfigText>{}</mes:JSONConfigText>
                        </mes:Details>
                    </mes:PageLayoutField>
                    <mes:PageLayoutField>
                        <mes:ClientID>SQL153/SQL_TEST_TestB_20160727_20161011_141529543_1474214</mes:ClientID>
                        <mes:PageLayoutID ClientID="SQL153/SQL_TEST_TestB_20160727_20161011_141529253_44642">Build Sequence Number Page Layout</mes:PageLayoutID>
                        <mes:ReportGroupAvailableFieldID ClientID="ERP_445">Description</mes:ReportGroupAvailableFieldID>
                        <mes:Details>
                            <mes:FirmID>Selenium-B1.199</mes:FirmID>
                            <mes:DisplayLabel>Description</mes:DisplayLabel>
                            <mes:DisplayOption1>33554432</mes:DisplayOption1>
                            <mes:DisplayOption2>0</mes:DisplayOption2>
                            <mes:HeaderColumnPosition>-1</mes:HeaderColumnPosition>
                            <mes:ViewColumnPosition>-1</mes:ViewColumnPosition>
                            <mes:ViewRowPosition>-1</mes:ViewRowPosition>
                            <mes:ViewFieldWidth>1</mes:ViewFieldWidth>
                            <mes:ViewFieldHeight>1</mes:ViewFieldHeight>
                            <mes:EditColumnPosition>1</mes:EditColumnPosition>
                            <mes:EditRowPosition>12</mes:EditRowPosition>
                            <mes:EditFieldWidth>5</mes:EditFieldWidth>
                            <mes:EditFieldHeight>1</mes:EditFieldHeight>
                            <mes:JSONConfigText>{}</mes:JSONConfigText>
                        </mes:Details>
                    </mes:PageLayoutField>
                    <mes:PageLayoutField>
                        <mes:ClientID>SQL153/SQL_TEST_TestB_20160727_20161011_141529560_1474215</mes:ClientID>
                        <mes:PageLayoutID ClientID="SQL153/SQL_TEST_TestB_20160727_20161011_141529253_44642">Build Sequence Number Page Layout</mes:PageLayoutID>
                        <mes:ReportGroupAvailableFieldID ClientID="ERP_509">BlankSpace</mes:ReportGroupAvailableFieldID>
                        <mes:Details>
                            <mes:FirmID>Selenium-B1.199</mes:FirmID>
                            <mes:DisplayLabel>Blank Space</mes:DisplayLabel>
                            <mes:DisplayOption1>0</mes:DisplayOption1>
                            <mes:DisplayOption2>0</mes:DisplayOption2>
                            <mes:HeaderColumnPosition>-1</mes:HeaderColumnPosition>
                            <mes:ViewColumnPosition>-1</mes:ViewColumnPosition>
                            <mes:ViewRowPosition>-1</mes:ViewRowPosition>
                            <mes:ViewFieldWidth>1</mes:ViewFieldWidth>
                            <mes:ViewFieldHeight>1</mes:ViewFieldHeight>
                            <mes:EditColumnPosition>6</mes:EditColumnPosition>
                            <mes:EditRowPosition>3</mes:EditRowPosition>
                            <mes:EditFieldWidth>1</mes:EditFieldWidth>
                            <mes:EditFieldHeight>1</mes:EditFieldHeight>
                            <mes:JSONConfigText>{}</mes:JSONConfigText>
                        </mes:Details>
                    </mes:PageLayoutField>
                    <mes:PageLayoutField>
                        <mes:ClientID>SQL153/SQL_TEST_TestB_20160727_20161011_141529578_1474216</mes:ClientID>
                        <mes:PageLayoutID ClientID="SQL153/SQL_TEST_TestB_20160727_20161011_141529253_44642">Build Sequence Number Page Layout</mes:PageLayoutID>
                        <mes:ReportGroupAvailableFieldID ClientID="ERP_510">StaticText</mes:ReportGroupAvailableFieldID>
                        <mes:Details>
                            <mes:FirmID>Selenium-B1.199</mes:FirmID>
                            <mes:StaticText>Total Projects</mes:StaticText>
                            <mes:DisplayLabel>Total Projects</mes:DisplayLabel>
                            <mes:DisplayOption1>0</mes:DisplayOption1>
                            <mes:DisplayOption2>160</mes:DisplayOption2>
                            <mes:HeaderColumnPosition>-1</mes:HeaderColumnPosition>
                            <mes:ViewColumnPosition>-1</mes:ViewColumnPosition>
                            <mes:ViewRowPosition>-1</mes:ViewRowPosition>
                            <mes:ViewFieldWidth>1</mes:ViewFieldWidth>
                            <mes:ViewFieldHeight>1</mes:ViewFieldHeight>
                            <mes:EditColumnPosition>10</mes:EditColumnPosition>
                            <mes:EditRowPosition>6</mes:EditRowPosition>
                            <mes:EditFieldWidth>1</mes:EditFieldWidth>
                            <mes:EditFieldHeight>1</mes:EditFieldHeight>
                            <mes:JSONConfigText>{}</mes:JSONConfigText>
                        </mes:Details>
                    </mes:PageLayoutField>
                    <mes:PageLayoutField>
                        <mes:ClientID>SQL153/SQL_TEST_TestB_20160727_20161011_141529593_1474217</mes:ClientID>
                        <mes:PageLayoutID ClientID="SQL153/SQL_TEST_TestB_20160727_20161011_141529253_44642">Build Sequence Number Page Layout</mes:PageLayoutID>
                        <mes:ReportGroupAvailableFieldID ClientID="ERP_510">StaticText</mes:ReportGroupAvailableFieldID>
                        <mes:Details>
                            <mes:FirmID>Selenium-B1.199</mes:FirmID>
                            <mes:StaticText>Number Remaining</mes:StaticText>
                            <mes:DisplayLabel>Number Remaining</mes:DisplayLabel>
                            <mes:DisplayOption1>0</mes:DisplayOption1>
                            <mes:DisplayOption2>160</mes:DisplayOption2>
                            <mes:HeaderColumnPosition>-1</mes:HeaderColumnPosition>
                            <mes:ViewColumnPosition>-1</mes:ViewColumnPosition>
                            <mes:ViewRowPosition>-1</mes:ViewRowPosition>
                            <mes:ViewFieldWidth>1</mes:ViewFieldWidth>
                            <mes:ViewFieldHeight>1</mes:ViewFieldHeight>
                            <mes:EditColumnPosition>10</mes:EditColumnPosition>
                            <mes:EditRowPosition>7</mes:EditRowPosition>
                            <mes:EditFieldWidth>1</mes:EditFieldWidth>
                            <mes:EditFieldHeight>1</mes:EditFieldHeight>
                            <mes:JSONConfigText>{}</mes:JSONConfigText>
                        </mes:Details>
                    </mes:PageLayoutField>
                    <mes:PageLayoutField>
                        <mes:ClientID>SQL153/SQL_TEST_TestB_20160727_20161011_141529620_1474218</mes:ClientID>
                        <mes:PageLayoutID ClientID="SQL153/SQL_TEST_TestB_20160727_20161011_141529253_44642">Build Sequence Number Page Layout</mes:PageLayoutID>
                        <mes:ReportGroupAvailableFieldID ClientID="192.168.123.194_Dev_Trunk_20110815_114047307_0">TotalDeadProjects</mes:ReportGroupAvailableFieldID>
                        <mes:Details>
                            <mes:FirmID>Selenium-B1.199</mes:FirmID>
                            <mes:DisplayLabel>Total Dead Projects</mes:DisplayLabel>
                            <mes:DisplayOption1>402653440</mes:DisplayOption1>
                            <mes:DisplayOption2>0</mes:DisplayOption2>
                            <mes:HeaderColumnPosition>-1</mes:HeaderColumnPosition>
                            <mes:ViewColumnPosition>-1</mes:ViewColumnPosition>
                            <mes:ViewRowPosition>-1</mes:ViewRowPosition>
                            <mes:ViewFieldWidth>1</mes:ViewFieldWidth>
                            <mes:ViewFieldHeight>1</mes:ViewFieldHeight>
                            <mes:EditColumnPosition>7</mes:EditColumnPosition>
                            <mes:EditRowPosition>6</mes:EditRowPosition>
                            <mes:EditFieldWidth>1</mes:EditFieldWidth>
                            <mes:EditFieldHeight>1</mes:EditFieldHeight>
                            <mes:JSONConfigText>{"NumberOfDecimals":""}</mes:JSONConfigText>
                        </mes:Details>
                    </mes:PageLayoutField>
                    <mes:PageLayoutField>
                        <mes:ClientID>SQL153/SQL_TEST_TestB_20160727_20161011_141529643_1474219</mes:ClientID>
                        <mes:PageLayoutID ClientID="SQL153/SQL_TEST_TestB_20160727_20161011_141529253_44642">Build Sequence Number Page Layout</mes:PageLayoutID>
                        <mes:ReportGroupAvailableFieldID ClientID="192.168.123.194_Dev_Trunk_20110815_114047306_1">TotalInactiveProjects</mes:ReportGroupAvailableFieldID>
                        <mes:Details>
                            <mes:FirmID>Selenium-B1.199</mes:FirmID>
                            <mes:DisplayLabel>Total Inactive Projects</mes:DisplayLabel>
                            <mes:DisplayOption1>402653440</mes:DisplayOption1>
                            <mes:DisplayOption2>0</mes:DisplayOption2>
                            <mes:HeaderColumnPosition>-1</mes:HeaderColumnPosition>
                            <mes:ViewColumnPosition>-1</mes:ViewColumnPosition>
                            <mes:ViewRowPosition>-1</mes:ViewRowPosition>
                            <mes:ViewFieldWidth>1</mes:ViewFieldWidth>
                            <mes:ViewFieldHeight>1</mes:ViewFieldHeight>
                            <mes:EditColumnPosition>11</mes:EditColumnPosition>
                            <mes:EditRowPosition>5</mes:EditRowPosition>
                            <mes:EditFieldWidth>1</mes:EditFieldWidth>
                            <mes:EditFieldHeight>1</mes:EditFieldHeight>
                            <mes:JSONConfigText>{"NumberOfDecimals":""}</mes:JSONConfigText>
                        </mes:Details>
                    </mes:PageLayoutField>
                    <mes:PageLayoutField>
                        <mes:ClientID>SQL153/SQL_TEST_TestB_20160727_20161011_141529677_1474220</mes:ClientID>
                        <mes:PageLayoutID ClientID="SQL153/SQL_TEST_TestB_20160727_20161011_141529253_44642">Build Sequence Number Page Layout</mes:PageLayoutID>
                        <mes:ReportGroupAvailableFieldID ClientID="ERP_510">StaticText</mes:ReportGroupAvailableFieldID>
                        <mes:Details>
                            <mes:FirmID>Selenium-B1.199</mes:FirmID>
                            <mes:StaticText>Active Projects</mes:StaticText>
                            <mes:DisplayLabel>Active Projects</mes:DisplayLabel>
                            <mes:DisplayOption1>0</mes:DisplayOption1>
                            <mes:DisplayOption2>160</mes:DisplayOption2>
                            <mes:HeaderColumnPosition>-1</mes:HeaderColumnPosition>
                            <mes:ViewColumnPosition>-1</mes:ViewColumnPosition>
                            <mes:ViewRowPosition>-1</mes:ViewRowPosition>
                            <mes:ViewFieldWidth>1</mes:ViewFieldWidth>
                            <mes:ViewFieldHeight>1</mes:ViewFieldHeight>
                            <mes:EditColumnPosition>6</mes:EditColumnPosition>
                            <mes:EditRowPosition>5</mes:EditRowPosition>
                            <mes:EditFieldWidth>1</mes:EditFieldWidth>
                            <mes:EditFieldHeight>1</mes:EditFieldHeight>
                            <mes:JSONConfigText>{}</mes:JSONConfigText>
                        </mes:Details>
                    </mes:PageLayoutField>
                    <mes:PageLayoutField>
                        <mes:ClientID>SQL153/SQL_TEST_TestB_20160727_20161011_141529695_1474221</mes:ClientID>
                        <mes:PageLayoutID ClientID="SQL153/SQL_TEST_TestB_20160727_20161011_141529253_44642">Build Sequence Number Page Layout</mes:PageLayoutID>
                        <mes:ReportGroupAvailableFieldID ClientID="192.168.123.194_Dev_Trunk_20110815_114047306_0">TotalActiveProjects</mes:ReportGroupAvailableFieldID>
                        <mes:Details>
                            <mes:FirmID>Selenium-B1.199</mes:FirmID>
                            <mes:DisplayLabel>Total Active Projects</mes:DisplayLabel>
                            <mes:DisplayOption1>402653440</mes:DisplayOption1>
                            <mes:DisplayOption2>0</mes:DisplayOption2>
                            <mes:HeaderColumnPosition>-1</mes:HeaderColumnPosition>
                            <mes:ViewColumnPosition>-1</mes:ViewColumnPosition>
                            <mes:ViewRowPosition>-1</mes:ViewRowPosition>
                            <mes:ViewFieldWidth>1</mes:ViewFieldWidth>
                            <mes:ViewFieldHeight>1</mes:ViewFieldHeight>
                            <mes:EditColumnPosition>7</mes:EditColumnPosition>
                            <mes:EditRowPosition>5</mes:EditRowPosition>
                            <mes:EditFieldWidth>1</mes:EditFieldWidth>
                            <mes:EditFieldHeight>1</mes:EditFieldHeight>
                            <mes:JSONConfigText>{"NumberOfDecimals":""}</mes:JSONConfigText>
                        </mes:Details>
                    </mes:PageLayoutField>
                    <mes:PageLayoutField>
                        <mes:ClientID>SQL153/SQL_TEST_TestB_20160727_20161011_141529711_1474222</mes:ClientID>
                        <mes:PageLayoutID ClientID="SQL153/SQL_TEST_TestB_20160727_20161011_141529253_44642">Build Sequence Number Page Layout</mes:PageLayoutID>
                        <mes:ReportGroupAvailableFieldID ClientID="ERP_510">StaticText</mes:ReportGroupAvailableFieldID>
                        <mes:Details>
                            <mes:FirmID>Selenium-B1.199</mes:FirmID>
                            <mes:StaticText>Number Completed</mes:StaticText>
                            <mes:DisplayLabel>Number Completed</mes:DisplayLabel>
                            <mes:DisplayOption1>0</mes:DisplayOption1>
                            <mes:DisplayOption2>160</mes:DisplayOption2>
                            <mes:HeaderColumnPosition>-1</mes:HeaderColumnPosition>
                            <mes:ViewColumnPosition>-1</mes:ViewColumnPosition>
                            <mes:ViewRowPosition>-1</mes:ViewRowPosition>
                            <mes:ViewFieldWidth>1</mes:ViewFieldWidth>
                            <mes:ViewFieldHeight>1</mes:ViewFieldHeight>
                            <mes:EditColumnPosition>6</mes:EditColumnPosition>
                            <mes:EditRowPosition>7</mes:EditRowPosition>
                            <mes:EditFieldWidth>1</mes:EditFieldWidth>
                            <mes:EditFieldHeight>1</mes:EditFieldHeight>
                            <mes:JSONConfigText>{}</mes:JSONConfigText>
                        </mes:Details>
                    </mes:PageLayoutField>
                    <mes:PageLayoutField>
                        <mes:ClientID>SQL153/SQL_TEST_TestB_20160727_20161011_141529745_1474223</mes:ClientID>
                        <mes:PageLayoutID ClientID="SQL153/SQL_TEST_TestB_20160727_20161011_141529253_44642">Build Sequence Number Page Layout</mes:PageLayoutID>
                        <mes:ReportGroupAvailableFieldID ClientID="bobnotebook/SQLEXPRESS_Trunk_20100517_162930506_0">NumProjectsNotComplete</mes:ReportGroupAvailableFieldID>
                        <mes:Details>
                            <mes:FirmID>Selenium-B1.199</mes:FirmID>
                            <mes:DisplayLabel>Projects Remaining</mes:DisplayLabel>
                            <mes:DisplayOption1>402653440</mes:DisplayOption1>
                            <mes:DisplayOption2>0</mes:DisplayOption2>
                            <mes:HeaderColumnPosition>-1</mes:HeaderColumnPosition>
                            <mes:ViewColumnPosition>-1</mes:ViewColumnPosition>
                            <mes:ViewRowPosition>-1</mes:ViewRowPosition>
                            <mes:ViewFieldWidth>1</mes:ViewFieldWidth>
                            <mes:ViewFieldHeight>1</mes:ViewFieldHeight>
                            <mes:EditColumnPosition>11</mes:EditColumnPosition>
                            <mes:EditRowPosition>7</mes:EditRowPosition>
                            <mes:EditFieldWidth>1</mes:EditFieldWidth>
                            <mes:EditFieldHeight>1</mes:EditFieldHeight>
                            <mes:JSONConfigText>{"NumberOfDecimals":""}</mes:JSONConfigText>
                        </mes:Details>
                    </mes:PageLayoutField>
                    <mes:PageLayoutField>
                        <mes:ClientID>SQL153/SQL_TEST_TestB_20160727_20161011_141529761_1474224</mes:ClientID>
                        <mes:PageLayoutID ClientID="SQL153/SQL_TEST_TestB_20160727_20161011_141529253_44642">Build Sequence Number Page Layout</mes:PageLayoutID>
                        <mes:ReportGroupAvailableFieldID ClientID="bobnotebook/SQLEXPRESS_Trunk_20100517_162930505_0">TotalProjects</mes:ReportGroupAvailableFieldID>
                        <mes:Details>
                            <mes:FirmID>Selenium-B1.199</mes:FirmID>
                            <mes:DisplayLabel>Total Projects</mes:DisplayLabel>
                            <mes:DisplayOption1>402653440</mes:DisplayOption1>
                            <mes:DisplayOption2>0</mes:DisplayOption2>
                            <mes:HeaderColumnPosition>-1</mes:HeaderColumnPosition>
                            <mes:ViewColumnPosition>-1</mes:ViewColumnPosition>
                            <mes:ViewRowPosition>-1</mes:ViewRowPosition>
                            <mes:ViewFieldWidth>1</mes:ViewFieldWidth>
                            <mes:ViewFieldHeight>1</mes:ViewFieldHeight>
                            <mes:EditColumnPosition>11</mes:EditColumnPosition>
                            <mes:EditRowPosition>6</mes:EditRowPosition>
                            <mes:EditFieldWidth>1</mes:EditFieldWidth>
                            <mes:EditFieldHeight>1</mes:EditFieldHeight>
                            <mes:JSONConfigText>{"NumberOfDecimals":""}</mes:JSONConfigText>
                        </mes:Details>
                    </mes:PageLayoutField>
                    <mes:PageLayoutField>
                        <mes:ClientID>SQL153/SQL_TEST_TestB_20160727_20161011_141529777_1474225</mes:ClientID>
                        <mes:PageLayoutID ClientID="SQL153/SQL_TEST_TestB_20160727_20161011_141529253_44642">Build Sequence Number Page Layout</mes:PageLayoutID>
                        <mes:ReportGroupAvailableFieldID ClientID="ERP_510">StaticText</mes:ReportGroupAvailableFieldID>
                        <mes:Details>
                            <mes:FirmID>Selenium-B1.199</mes:FirmID>
                            <mes:StaticText>Inactive Projects</mes:StaticText>
                            <mes:DisplayLabel>Inactive Projects</mes:DisplayLabel>
                            <mes:DisplayOption1>0</mes:DisplayOption1>
                            <mes:DisplayOption2>160</mes:DisplayOption2>
                            <mes:HeaderColumnPosition>-1</mes:HeaderColumnPosition>
                            <mes:ViewColumnPosition>-1</mes:ViewColumnPosition>
                            <mes:ViewRowPosition>-1</mes:ViewRowPosition>
                            <mes:ViewFieldWidth>1</mes:ViewFieldWidth>
                            <mes:ViewFieldHeight>1</mes:ViewFieldHeight>
                            <mes:EditColumnPosition>10</mes:EditColumnPosition>
                            <mes:EditRowPosition>5</mes:EditRowPosition>
                            <mes:EditFieldWidth>1</mes:EditFieldWidth>
                            <mes:EditFieldHeight>1</mes:EditFieldHeight>
                            <mes:JSONConfigText>{}</mes:JSONConfigText>
                        </mes:Details>
                    </mes:PageLayoutField>
                    <mes:PageLayoutField>
                        <mes:ClientID>SQL153/SQL_TEST_TestB_20160727_20161011_141529792_1474226</mes:ClientID>
                        <mes:PageLayoutID ClientID="SQL153/SQL_TEST_TestB_20160727_20161011_141529253_44642">Build Sequence Number Page Layout</mes:PageLayoutID>
                        <mes:ReportGroupAvailableFieldID ClientID="ERP_510">StaticText</mes:ReportGroupAvailableFieldID>
                        <mes:Details>
                            <mes:FirmID>Selenium-B1.199</mes:FirmID>
                            <mes:StaticText>Dead Projects</mes:StaticText>
                            <mes:DisplayLabel>Dead Projects</mes:DisplayLabel>
                            <mes:DisplayOption1>0</mes:DisplayOption1>
                            <mes:DisplayOption2>160</mes:DisplayOption2>
                            <mes:HeaderColumnPosition>-1</mes:HeaderColumnPosition>
                            <mes:ViewColumnPosition>-1</mes:ViewColumnPosition>
                            <mes:ViewRowPosition>-1</mes:ViewRowPosition>
                            <mes:ViewFieldWidth>1</mes:ViewFieldWidth>
                            <mes:ViewFieldHeight>1</mes:ViewFieldHeight>
                            <mes:EditColumnPosition>6</mes:EditColumnPosition>
                            <mes:EditRowPosition>6</mes:EditRowPosition>
                            <mes:EditFieldWidth>1</mes:EditFieldWidth>
                            <mes:EditFieldHeight>1</mes:EditFieldHeight>
                            <mes:JSONConfigText>{}</mes:JSONConfigText>
                        </mes:Details>
                    </mes:PageLayoutField>
                    <mes:PageLayoutField>
                        <mes:ClientID>SQL153/SQL_TEST_TestB_20160727_20161011_141529826_1474227</mes:ClientID>
                        <mes:PageLayoutID ClientID="SQL153/SQL_TEST_TestB_20160727_20161011_141529253_44642">Build Sequence Number Page Layout</mes:PageLayoutID>
                        <mes:ReportGroupAvailableFieldID ClientID="ERP_1331">IssuesAndAlerts</mes:ReportGroupAvailableFieldID>
                        <mes:Details>
                            <mes:FirmID>Selenium-B1.199</mes:FirmID>
                            <mes:DisplayLabel>Issues And Alerts</mes:DisplayLabel>
                            <mes:DisplayOption1>268435712</mes:DisplayOption1>
                            <mes:DisplayOption2>0</mes:DisplayOption2>
                            <mes:HeaderColumnPosition>-1</mes:HeaderColumnPosition>
                            <mes:ViewColumnPosition>-1</mes:ViewColumnPosition>
                            <mes:ViewRowPosition>-1</mes:ViewRowPosition>
                            <mes:ViewFieldWidth>1</mes:ViewFieldWidth>
                            <mes:ViewFieldHeight>1</mes:ViewFieldHeight>
                            <mes:EditColumnPosition>6</mes:EditColumnPosition>
                            <mes:EditRowPosition>13</mes:EditRowPosition>
                            <mes:EditFieldWidth>6</mes:EditFieldWidth>
                            <mes:EditFieldHeight>2</mes:EditFieldHeight>
                            <mes:JSONConfigText>{}</mes:JSONConfigText>
                        </mes:Details>
                    </mes:PageLayoutField>
                    <mes:PageLayoutField>
                        <mes:ClientID>SQL153/SQL_TEST_TestB_20160727_20161011_141529843_1474228</mes:ClientID>
                        <mes:PageLayoutID ClientID="SQL153/SQL_TEST_TestB_20160727_20161011_141529253_44642">Build Sequence Number Page Layout</mes:PageLayoutID>
                        <mes:ReportGroupAvailableFieldID ClientID="ERP_508">BlankRow</mes:ReportGroupAvailableFieldID>
                        <mes:Details>
                            <mes:FirmID>Selenium-B1.199</mes:FirmID>
                            <mes:DisplayLabel>Blank Row</mes:DisplayLabel>
                            <mes:DisplayOption1>0</mes:DisplayOption1>
                            <mes:DisplayOption2>0</mes:DisplayOption2>
                            <mes:HeaderColumnPosition>-1</mes:HeaderColumnPosition>
                            <mes:ViewColumnPosition>-1</mes:ViewColumnPosition>
                            <mes:ViewRowPosition>-1</mes:ViewRowPosition>
                            <mes:ViewFieldWidth>1</mes:ViewFieldWidth>
                            <mes:ViewFieldHeight>1</mes:ViewFieldHeight>
                            <mes:EditColumnPosition>1</mes:EditColumnPosition>
                            <mes:EditRowPosition>9</mes:EditRowPosition>
                            <mes:EditFieldWidth>1</mes:EditFieldWidth>
                            <mes:EditFieldHeight>1</mes:EditFieldHeight>
                            <mes:JSONConfigText>{}</mes:JSONConfigText>
                        </mes:Details>
                    </mes:PageLayoutField>
                    <mes:PageLayoutField>
                        <mes:ClientID>SQL153/SQL_TEST_TestB_20160727_20161011_141529858_1474229</mes:ClientID>
                        <mes:PageLayoutID ClientID="SQL153/SQL_TEST_TestB_20160727_20161011_141529253_44642">Build Sequence Number Page Layout</mes:PageLayoutID>
                        <mes:ReportGroupAvailableFieldID ClientID="ERP_509">BlankSpace</mes:ReportGroupAvailableFieldID>
                        <mes:Details>
                            <mes:FirmID>Selenium-B1.199</mes:FirmID>
                            <mes:DisplayLabel>Blank Space</mes:DisplayLabel>
                            <mes:DisplayOption1>0</mes:DisplayOption1>
                            <mes:DisplayOption2>0</mes:DisplayOption2>
                            <mes:HeaderColumnPosition>-1</mes:HeaderColumnPosition>
                            <mes:ViewColumnPosition>-1</mes:ViewColumnPosition>
                            <mes:ViewRowPosition>-1</mes:ViewRowPosition>
                            <mes:ViewFieldWidth>1</mes:ViewFieldWidth>
                            <mes:ViewFieldHeight>1</mes:ViewFieldHeight>
                            <mes:EditColumnPosition>8</mes:EditColumnPosition>
                            <mes:EditRowPosition>7</mes:EditRowPosition>
                            <mes:EditFieldWidth>1</mes:EditFieldWidth>
                            <mes:EditFieldHeight>1</mes:EditFieldHeight>
                            <mes:JSONConfigText>{}</mes:JSONConfigText>
                        </mes:Details>
                    </mes:PageLayoutField>
                    <mes:PageLayoutField>
                        <mes:ClientID>SQL153/SQL_TEST_TestB_20160727_20161011_141529872_1474230</mes:ClientID>
                        <mes:PageLayoutID ClientID="SQL153/SQL_TEST_TestB_20160727_20161011_141529253_44642">Build Sequence Number Page Layout</mes:PageLayoutID>
                        <mes:ReportGroupAvailableFieldID ClientID="ERP_509">BlankSpace</mes:ReportGroupAvailableFieldID>
                        <mes:Details>
                            <mes:FirmID>Selenium-B1.199</mes:FirmID>
                            <mes:DisplayLabel>Blank Space</mes:DisplayLabel>
                            <mes:DisplayOption1>0</mes:DisplayOption1>
                            <mes:DisplayOption2>0</mes:DisplayOption2>
                            <mes:HeaderColumnPosition>-1</mes:HeaderColumnPosition>
                            <mes:ViewColumnPosition>-1</mes:ViewColumnPosition>
                            <mes:ViewRowPosition>-1</mes:ViewRowPosition>
                            <mes:ViewFieldWidth>1</mes:ViewFieldWidth>
                            <mes:ViewFieldHeight>1</mes:ViewFieldHeight>
                            <mes:EditColumnPosition>8</mes:EditColumnPosition>
                            <mes:EditRowPosition>5</mes:EditRowPosition>
                            <mes:EditFieldWidth>1</mes:EditFieldWidth>
                            <mes:EditFieldHeight>1</mes:EditFieldHeight>
                            <mes:JSONConfigText>{}</mes:JSONConfigText>
                        </mes:Details>
                    </mes:PageLayoutField>
                    <mes:PageLayoutField>
                        <mes:ClientID>SQL153/SQL_TEST_TestB_20160727_20161011_141529891_1474231</mes:ClientID>
                        <mes:PageLayoutID ClientID="SQL153/SQL_TEST_TestB_20160727_20161011_141529253_44642">Build Sequence Number Page Layout</mes:PageLayoutID>
                        <mes:ReportGroupAvailableFieldID ClientID="ERP_509">BlankSpace</mes:ReportGroupAvailableFieldID>
                        <mes:Details>
                            <mes:FirmID>Selenium-B1.199</mes:FirmID>
                            <mes:DisplayLabel>Blank Space</mes:DisplayLabel>
                            <mes:DisplayOption1>0</mes:DisplayOption1>
                            <mes:DisplayOption2>0</mes:DisplayOption2>
                            <mes:HeaderColumnPosition>-1</mes:HeaderColumnPosition>
                            <mes:ViewColumnPosition>-1</mes:ViewColumnPosition>
                            <mes:ViewRowPosition>-1</mes:ViewRowPosition>
                            <mes:ViewFieldWidth>1</mes:ViewFieldWidth>
                            <mes:ViewFieldHeight>1</mes:ViewFieldHeight>
                            <mes:EditColumnPosition>8</mes:EditColumnPosition>
                            <mes:EditRowPosition>6</mes:EditRowPosition>
                            <mes:EditFieldWidth>1</mes:EditFieldWidth>
                            <mes:EditFieldHeight>1</mes:EditFieldHeight>
                            <mes:JSONConfigText>{}</mes:JSONConfigText>
                        </mes:Details>
                    </mes:PageLayoutField>
                    <mes:PageLayoutField>
                        <mes:ClientID>SQL153/SQL_TEST_TestB_20160727_20161011_141529905_1474232</mes:ClientID>
                        <mes:PageLayoutID ClientID="SQL153/SQL_TEST_TestB_20160727_20161011_141529253_44642">Build Sequence Number Page Layout</mes:PageLayoutID>
                        <mes:ReportGroupAvailableFieldID ClientID="ERP_509">BlankSpace</mes:ReportGroupAvailableFieldID>
                        <mes:Details>
                            <mes:FirmID>Selenium-B1.199</mes:FirmID>
                            <mes:DisplayLabel>Blank Space</mes:DisplayLabel>
                            <mes:DisplayOption1>0</mes:DisplayOption1>
                            <mes:DisplayOption2>0</mes:DisplayOption2>
                            <mes:HeaderColumnPosition>-1</mes:HeaderColumnPosition>
                            <mes:ViewColumnPosition>-1</mes:ViewColumnPosition>
                            <mes:ViewRowPosition>-1</mes:ViewRowPosition>
                            <mes:ViewFieldWidth>1</mes:ViewFieldWidth>
                            <mes:ViewFieldHeight>1</mes:ViewFieldHeight>
                            <mes:EditColumnPosition>8</mes:EditColumnPosition>
                            <mes:EditRowPosition>8</mes:EditRowPosition>
                            <mes:EditFieldWidth>1</mes:EditFieldWidth>
                            <mes:EditFieldHeight>1</mes:EditFieldHeight>
                            <mes:JSONConfigText>{}</mes:JSONConfigText>
                        </mes:Details>
                    </mes:PageLayoutField>
                    <mes:PageLayoutField>
                        <mes:ClientID>SQL153/SQL_TEST_TestB_20160727_20161011_141529922_1474233</mes:ClientID>
                        <mes:PageLayoutID ClientID="SQL153/SQL_TEST_TestB_20160727_20161011_141529253_44642">Build Sequence Number Page Layout</mes:PageLayoutID>
                        <mes:ReportGroupAvailableFieldID ClientID="ERP_509">BlankSpace</mes:ReportGroupAvailableFieldID>
                        <mes:Details>
                            <mes:FirmID>Selenium-B1.199</mes:FirmID>
                            <mes:DisplayLabel>Blank Space</mes:DisplayLabel>
                            <mes:DisplayOption1>0</mes:DisplayOption1>
                            <mes:DisplayOption2>0</mes:DisplayOption2>
                            <mes:HeaderColumnPosition>-1</mes:HeaderColumnPosition>
                            <mes:ViewColumnPosition>-1</mes:ViewColumnPosition>
                            <mes:ViewRowPosition>-1</mes:ViewRowPosition>
                            <mes:ViewFieldWidth>1</mes:ViewFieldWidth>
                            <mes:ViewFieldHeight>1</mes:ViewFieldHeight>
                            <mes:EditColumnPosition>9</mes:EditColumnPosition>
                            <mes:EditRowPosition>8</mes:EditRowPosition>
                            <mes:EditFieldWidth>1</mes:EditFieldWidth>
                            <mes:EditFieldHeight>1</mes:EditFieldHeight>
                            <mes:JSONConfigText>{}</mes:JSONConfigText>
                        </mes:Details>
                    </mes:PageLayoutField>
                    <mes:PageLayoutField>
                        <mes:ClientID>SQL153/SQL_TEST_TestB_20160727_20161011_141529936_1474234</mes:ClientID>
                        <mes:PageLayoutID ClientID="SQL153/SQL_TEST_TestB_20160727_20161011_141529253_44642">Build Sequence Number Page Layout</mes:PageLayoutID>
                        <mes:ReportGroupAvailableFieldID ClientID="ERP_509">BlankSpace</mes:ReportGroupAvailableFieldID>
                        <mes:Details>
                            <mes:FirmID>Selenium-B1.199</mes:FirmID>
                            <mes:DisplayLabel>Blank Space</mes:DisplayLabel>
                            <mes:DisplayOption1>0</mes:DisplayOption1>
                            <mes:DisplayOption2>0</mes:DisplayOption2>
                            <mes:HeaderColumnPosition>-1</mes:HeaderColumnPosition>
                            <mes:ViewColumnPosition>-1</mes:ViewColumnPosition>
                            <mes:ViewRowPosition>-1</mes:ViewRowPosition>
                            <mes:ViewFieldWidth>1</mes:ViewFieldWidth>
                            <mes:ViewFieldHeight>1</mes:ViewFieldHeight>
                            <mes:EditColumnPosition>9</mes:EditColumnPosition>
                            <mes:EditRowPosition>5</mes:EditRowPosition>
                            <mes:EditFieldWidth>1</mes:EditFieldWidth>
                            <mes:EditFieldHeight>1</mes:EditFieldHeight>
                            <mes:JSONConfigText>{}</mes:JSONConfigText>
                        </mes:Details>
                    </mes:PageLayoutField>
                    <mes:PageLayoutField>
                        <mes:ClientID>SQL153/SQL_TEST_TestB_20160727_20161011_141529952_1474235</mes:ClientID>
                        <mes:PageLayoutID ClientID="SQL153/SQL_TEST_TestB_20160727_20161011_141529253_44642">Build Sequence Number Page Layout</mes:PageLayoutID>
                        <mes:ReportGroupAvailableFieldID ClientID="ERP_509">BlankSpace</mes:ReportGroupAvailableFieldID>
                        <mes:Details>
                            <mes:FirmID>Selenium-B1.199</mes:FirmID>
                            <mes:DisplayLabel>Blank Space</mes:DisplayLabel>
                            <mes:DisplayOption1>0</mes:DisplayOption1>
                            <mes:DisplayOption2>0</mes:DisplayOption2>
                            <mes:HeaderColumnPosition>-1</mes:HeaderColumnPosition>
                            <mes:ViewColumnPosition>-1</mes:ViewColumnPosition>
                            <mes:ViewRowPosition>-1</mes:ViewRowPosition>
                            <mes:ViewFieldWidth>1</mes:ViewFieldWidth>
                            <mes:ViewFieldHeight>1</mes:ViewFieldHeight>
                            <mes:EditColumnPosition>9</mes:EditColumnPosition>
                            <mes:EditRowPosition>6</mes:EditRowPosition>
                            <mes:EditFieldWidth>1</mes:EditFieldWidth>
                            <mes:EditFieldHeight>1</mes:EditFieldHeight>
                            <mes:JSONConfigText>{}</mes:JSONConfigText>
                        </mes:Details>
                    </mes:PageLayoutField>
                    <mes:PageLayoutField>
                        <mes:ClientID>SQL153/SQL_TEST_TestB_20160727_20161011_141529970_1474236</mes:ClientID>
                        <mes:PageLayoutID ClientID="SQL153/SQL_TEST_TestB_20160727_20161011_141529253_44642">Build Sequence Number Page Layout</mes:PageLayoutID>
                        <mes:ReportGroupAvailableFieldID ClientID="ERP_509">BlankSpace</mes:ReportGroupAvailableFieldID>
                        <mes:Details>
                            <mes:FirmID>Selenium-B1.199</mes:FirmID>
                            <mes:DisplayLabel>Blank Space</mes:DisplayLabel>
                            <mes:DisplayOption1>0</mes:DisplayOption1>
                            <mes:DisplayOption2>0</mes:DisplayOption2>
                            <mes:HeaderColumnPosition>-1</mes:HeaderColumnPosition>
                            <mes:ViewColumnPosition>-1</mes:ViewColumnPosition>
                            <mes:ViewRowPosition>-1</mes:ViewRowPosition>
                            <mes:ViewFieldWidth>1</mes:ViewFieldWidth>
                            <mes:ViewFieldHeight>1</mes:ViewFieldHeight>
                            <mes:EditColumnPosition>9</mes:EditColumnPosition>
                            <mes:EditRowPosition>7</mes:EditRowPosition>
                            <mes:EditFieldWidth>1</mes:EditFieldWidth>
                            <mes:EditFieldHeight>1</mes:EditFieldHeight>
                            <mes:JSONConfigText>{}</mes:JSONConfigText>
                        </mes:Details>
                    </mes:PageLayoutField>
                    <mes:PageLayoutField>
                        <mes:ClientID>SQL153/SQL_TEST_TestB_20160727_20161011_141529989_1474237</mes:ClientID>
                        <mes:PageLayoutID ClientID="SQL153/SQL_TEST_TestB_20160727_20161011_141529253_44642">Build Sequence Number Page Layout</mes:PageLayoutID>
                        <mes:ReportGroupAvailableFieldID ClientID="bobnotebook/SQLEXPRESS_Trunk_20100517_162930507_1">CapProjectsInProgram</mes:ReportGroupAvailableFieldID>
                        <mes:Details>
                            <mes:FirmID>Selenium-B1.199</mes:FirmID>
                            <mes:DisplayLabel>Projects Summary</mes:DisplayLabel>
                            <mes:DisplayOption1>0</mes:DisplayOption1>
                            <mes:DisplayOption2>2</mes:DisplayOption2>
                            <mes:HeaderColumnPosition>-1</mes:HeaderColumnPosition>
                            <mes:ViewColumnPosition>-1</mes:ViewColumnPosition>
                            <mes:ViewRowPosition>-1</mes:ViewRowPosition>
                            <mes:ViewFieldWidth>1</mes:ViewFieldWidth>
                            <mes:ViewFieldHeight>1</mes:ViewFieldHeight>
                            <mes:EditColumnPosition>1</mes:EditColumnPosition>
                            <mes:EditRowPosition>14</mes:EditRowPosition>
                            <mes:EditFieldWidth>5</mes:EditFieldWidth>
                            <mes:EditFieldHeight>1</mes:EditFieldHeight>
                            <mes:JSONConfigText>{"EditModeDefaultValue":""}</mes:JSONConfigText>
                        </mes:Details>
                    </mes:PageLayoutField>
                    <mes:PageLayoutField>
                        <mes:ClientID>SQL153/SQL_TEST_TestB_20160727_20161011_141530004_1474238</mes:ClientID>
                        <mes:PageLayoutID ClientID="SQL153/SQL_TEST_TestB_20160727_20161011_141529253_44642">Build Sequence Number Page Layout</mes:PageLayoutID>
                        <mes:ReportGroupAvailableFieldID ClientID="bobnotebook/SQLEXPRESS_Trunk_20100517_162930507_2">PercentCompleteByCount</mes:ReportGroupAvailableFieldID>
                        <mes:Details>
                            <mes:FirmID>Selenium-B1.199</mes:FirmID>
                            <mes:DisplayLabel>% Complete</mes:DisplayLabel>
                            <mes:DisplayOption1>167772160</mes:DisplayOption1>
                            <mes:DisplayOption2>0</mes:DisplayOption2>
                            <mes:HeaderColumnPosition>-1</mes:HeaderColumnPosition>
                            <mes:ViewColumnPosition>-1</mes:ViewColumnPosition>
                            <mes:ViewRowPosition>-1</mes:ViewRowPosition>
                            <mes:ViewFieldWidth>1</mes:ViewFieldWidth>
                            <mes:ViewFieldHeight>1</mes:ViewFieldHeight>
                            <mes:EditColumnPosition>6</mes:EditColumnPosition>
                            <mes:EditRowPosition>8</mes:EditRowPosition>
                            <mes:EditFieldWidth>2</mes:EditFieldWidth>
                            <mes:EditFieldHeight>1</mes:EditFieldHeight>
                            <mes:JSONConfigText>{"EditModeDefaultValue":"","NumberOfDecimals":"1"}</mes:JSONConfigText>
                        </mes:Details>
                    </mes:PageLayoutField>
                    <mes:PageLayoutField>
                        <mes:ClientID>SQL153/SQL_TEST_TestB_20160727_20161011_141530032_1474239</mes:ClientID>
                        <mes:PageLayoutID ClientID="SQL153/SQL_TEST_TestB_20160727_20161011_141529253_44642">Build Sequence Number Page Layout</mes:PageLayoutID>
                        <mes:ReportGroupAvailableFieldID ClientID="bobWin_Dev_Trunk_20150423_205501453_0">DefaultWorkWeekends</mes:ReportGroupAvailableFieldID>
                        <mes:Details>
                            <mes:FirmID>Selenium-B1.199</mes:FirmID>
                            <mes:DisplayLabel>Default Work Weekends</mes:DisplayLabel>
                            <mes:DisplayOption1>33554432</mes:DisplayOption1>
                            <mes:DisplayOption2>0</mes:DisplayOption2>
                            <mes:HeaderColumnPosition>-1</mes:HeaderColumnPosition>
                            <mes:ViewColumnPosition>-1</mes:ViewColumnPosition>
                            <mes:ViewRowPosition>-1</mes:ViewRowPosition>
                            <mes:ViewFieldWidth>1</mes:ViewFieldWidth>
                            <mes:ViewFieldHeight>1</mes:ViewFieldHeight>
                            <mes:EditColumnPosition>10</mes:EditColumnPosition>
                            <mes:EditRowPosition>10</mes:EditRowPosition>
                            <mes:EditFieldWidth>2</mes:EditFieldWidth>
                            <mes:EditFieldHeight>1</mes:EditFieldHeight>
                            <mes:JSONConfigText>{}</mes:JSONConfigText>
                        </mes:Details>
                    </mes:PageLayoutField>
                    <mes:PageLayoutField>
                        <mes:ClientID>SQL153/SQL_TEST_TestB_20160727_20161011_141530047_1474240</mes:ClientID>
                        <mes:PageLayoutID ClientID="SQL153/SQL_TEST_TestB_20160727_20161011_141529253_44642">Build Sequence Number Page Layout</mes:PageLayoutID>
                        <mes:ReportGroupAvailableFieldID ClientID="MORTVM_Dev_Trunk_20150105_133726554_0">DefaultHolidayScheduleID</mes:ReportGroupAvailableFieldID>
                        <mes:Details>
                            <mes:FirmID>Selenium-B1.199</mes:FirmID>
                            <mes:DisplayLabel>Default Holiday Schedule</mes:DisplayLabel>
                            <mes:DisplayOption1>33554432</mes:DisplayOption1>
                            <mes:DisplayOption2>0</mes:DisplayOption2>
                            <mes:HeaderColumnPosition>-1</mes:HeaderColumnPosition>
                            <mes:ViewColumnPosition>-1</mes:ViewColumnPosition>
                            <mes:ViewRowPosition>-1</mes:ViewRowPosition>
                            <mes:ViewFieldWidth>1</mes:ViewFieldWidth>
                            <mes:ViewFieldHeight>1</mes:ViewFieldHeight>
                            <mes:EditColumnPosition>6</mes:EditColumnPosition>
                            <mes:EditRowPosition>10</mes:EditRowPosition>
                            <mes:EditFieldWidth>2</mes:EditFieldWidth>
                            <mes:EditFieldHeight>1</mes:EditFieldHeight>
                            <mes:JSONConfigText>{}</mes:JSONConfigText>
                        </mes:Details>
                    </mes:PageLayoutField>
                    <mes:PageLayoutField>
                        <mes:ClientID>SQL153/SQL_TEST_TestB_20160727_20161011_141530063_1474241</mes:ClientID>
                        <mes:PageLayoutID ClientID="SQL153/SQL_TEST_TestB_20160727_20161011_141529253_44642">Build Sequence Number Page Layout</mes:PageLayoutID>
                        <mes:ReportGroupAvailableFieldID ClientID="ERP_509">BlankSpace</mes:ReportGroupAvailableFieldID>
                        <mes:Details>
                            <mes:FirmID>Selenium-B1.199</mes:FirmID>
                            <mes:DisplayLabel>Blank Space</mes:DisplayLabel>
                            <mes:DisplayOption1>0</mes:DisplayOption1>
                            <mes:DisplayOption2>0</mes:DisplayOption2>
                            <mes:HeaderColumnPosition>-1</mes:HeaderColumnPosition>
                            <mes:ViewColumnPosition>-1</mes:ViewColumnPosition>
                            <mes:ViewRowPosition>-1</mes:ViewRowPosition>
                            <mes:ViewFieldWidth>1</mes:ViewFieldWidth>
                            <mes:ViewFieldHeight>1</mes:ViewFieldHeight>
                            <mes:EditColumnPosition>12</mes:EditColumnPosition>
                            <mes:EditRowPosition>6</mes:EditRowPosition>
                            <mes:EditFieldWidth>1</mes:EditFieldWidth>
                            <mes:EditFieldHeight>1</mes:EditFieldHeight>
                            <mes:JSONConfigText>{}</mes:JSONConfigText>
                        </mes:Details>
                    </mes:PageLayoutField>
                    <mes:PageLayoutField>
                        <mes:ClientID>SQL153/SQL_TEST_TestB_20160727_20161011_141530078_1474242</mes:ClientID>
                        <mes:PageLayoutID ClientID="SQL153/SQL_TEST_TestB_20160727_20161011_141529253_44642">Build Sequence Number Page Layout</mes:PageLayoutID>
                        <mes:ReportGroupAvailableFieldID ClientID="ERP_509">BlankSpace</mes:ReportGroupAvailableFieldID>
                        <mes:Details>
                            <mes:FirmID>Selenium-B1.199</mes:FirmID>
                            <mes:DisplayLabel>Blank Space</mes:DisplayLabel>
                            <mes:DisplayOption1>0</mes:DisplayOption1>
                            <mes:DisplayOption2>0</mes:DisplayOption2>
                            <mes:HeaderColumnPosition>-1</mes:HeaderColumnPosition>
                            <mes:ViewColumnPosition>-1</mes:ViewColumnPosition>
                            <mes:ViewRowPosition>-1</mes:ViewRowPosition>
                            <mes:ViewFieldWidth>1</mes:ViewFieldWidth>
                            <mes:ViewFieldHeight>1</mes:ViewFieldHeight>
                            <mes:EditColumnPosition>12</mes:EditColumnPosition>
                            <mes:EditRowPosition>7</mes:EditRowPosition>
                            <mes:EditFieldWidth>1</mes:EditFieldWidth>
                            <mes:EditFieldHeight>1</mes:EditFieldHeight>
                            <mes:JSONConfigText>{}</mes:JSONConfigText>
                        </mes:Details>
                    </mes:PageLayoutField>
                    <mes:PageLayoutField>
                        <mes:ClientID>SQL153/SQL_TEST_TestB_20160727_20161011_141530094_1474243</mes:ClientID>
                        <mes:PageLayoutID ClientID="SQL153/SQL_TEST_TestB_20160727_20161011_141529253_44642">Build Sequence Number Page Layout</mes:PageLayoutID>
                        <mes:ReportGroupAvailableFieldID ClientID="ERP_510">StaticText</mes:ReportGroupAvailableFieldID>
                        <mes:Details>
                            <mes:FirmID>Selenium-B1.199</mes:FirmID>
                            <mes:StaticText>&lt;div style="width: 500px;">&lt;/div></mes:StaticText>
                            <mes:DisplayLabel>&lt;div style="width: 500px;">&lt;/div></mes:DisplayLabel>
                            <mes:DisplayOption1>0</mes:DisplayOption1>
                            <mes:DisplayOption2>536870912</mes:DisplayOption2>
                            <mes:HeaderColumnPosition>-1</mes:HeaderColumnPosition>
                            <mes:ViewColumnPosition>-1</mes:ViewColumnPosition>
                            <mes:ViewRowPosition>-1</mes:ViewRowPosition>
                            <mes:ViewFieldWidth>1</mes:ViewFieldWidth>
                            <mes:ViewFieldHeight>1</mes:ViewFieldHeight>
                            <mes:EditColumnPosition>1</mes:EditColumnPosition>
                            <mes:EditRowPosition>15</mes:EditRowPosition>
                            <mes:EditFieldWidth>5</mes:EditFieldWidth>
                            <mes:EditFieldHeight>1</mes:EditFieldHeight>
                            <mes:JSONConfigText>{}</mes:JSONConfigText>
                        </mes:Details>
                    </mes:PageLayoutField>
                    <mes:PageLayoutField>
                        <mes:ClientID>SQL153/SQL_TEST_TestB_20160727_20161011_141530127_1474244</mes:ClientID>
                        <mes:PageLayoutID ClientID="SQL153/SQL_TEST_TestB_20160727_20161011_141529253_44642">Build Sequence Number Page Layout</mes:PageLayoutID>
                        <mes:ReportGroupAvailableFieldID ClientID="INNAPC_Dev_Trunk_20160809_162654156_0">EntityEmail</mes:ReportGroupAvailableFieldID>
                        <mes:Details>
                            <mes:FirmID>Selenium-B1.199</mes:FirmID>
                            <mes:DisplayLabel>Entity Email</mes:DisplayLabel>
                            <mes:DisplayOption1>33554432</mes:DisplayOption1>
                            <mes:DisplayOption2>0</mes:DisplayOption2>
                            <mes:HeaderColumnPosition>-1</mes:HeaderColumnPosition>
                            <mes:ViewColumnPosition>-1</mes:ViewColumnPosition>
                            <mes:ViewRowPosition>-1</mes:ViewRowPosition>
                            <mes:ViewFieldWidth>1</mes:ViewFieldWidth>
                            <mes:ViewFieldHeight>1</mes:ViewFieldHeight>
                            <mes:EditColumnPosition>1</mes:EditColumnPosition>
                            <mes:EditRowPosition>11</mes:EditRowPosition>
                            <mes:EditFieldWidth>5</mes:EditFieldWidth>
                            <mes:EditFieldHeight>1</mes:EditFieldHeight>
                            <mes:JSONConfigText>{}</mes:JSONConfigText>
                        </mes:Details>
                    </mes:PageLayoutField>
                    <mes:PageLayoutField>
                        <mes:ClientID>SQL153/SQL_TEST_TestB_20160727_20161011_141530165_1474245</mes:ClientID>
                        <mes:PageLayoutID ClientID="SQL153/SQL_TEST_TestB_20160727_20161011_141529253_44642">Build Sequence Number Page Layout</mes:PageLayoutID>
                        <mes:ReportGroupAvailableFieldID ClientID="bobWin_Dev_Patch5_20140903_145252383_0">SequenceNumber</mes:ReportGroupAvailableFieldID>
                        <mes:Details>
                            <mes:FirmID>Selenium-B1.199</mes:FirmID>
                            <mes:DisplayLabel>Sequence Number</mes:DisplayLabel>
                            <mes:DisplayOption1>134234112</mes:DisplayOption1>
                            <mes:DisplayOption2>0</mes:DisplayOption2>
                            <mes:HeaderColumnPosition>-1</mes:HeaderColumnPosition>
                            <mes:ViewColumnPosition>-1</mes:ViewColumnPosition>
                            <mes:ViewRowPosition>-1</mes:ViewRowPosition>
                            <mes:ViewFieldWidth>1</mes:ViewFieldWidth>
                            <mes:ViewFieldHeight>1</mes:ViewFieldHeight>
                            <mes:EditColumnPosition>1</mes:EditColumnPosition>
                            <mes:EditRowPosition>16</mes:EditRowPosition>
                            <mes:EditFieldWidth>1</mes:EditFieldWidth>
                            <mes:EditFieldHeight>1</mes:EditFieldHeight>
                            <mes:JSONConfigText>{}</mes:JSONConfigText>
                        </mes:Details>
                    </mes:PageLayoutField>
                    <mes:PageLayoutField>
                        <mes:ClientID>SQL153/SQL_TEST_TestB_20160727_20161011_141530182_1474246</mes:ClientID>
                        <mes:PageLayoutID ClientID="SQL153/SQL_TEST_TestB_20160727_20161011_141529253_44642">Build Sequence Number Page Layout</mes:PageLayoutID>
                        <mes:ReportGroupAvailableFieldID ClientID="bobWin_Dev_Patch5_20140903_145252383_1">SiteSequenceNumber</mes:ReportGroupAvailableFieldID>
                        <mes:Details>
                            <mes:FirmID>Selenium-B1.199</mes:FirmID>
                            <mes:DisplayLabel>Site Sequence Number</mes:DisplayLabel>
                            <mes:DisplayOption1>402669568</mes:DisplayOption1>
                            <mes:DisplayOption2>0</mes:DisplayOption2>
                            <mes:HeaderColumnPosition>-1</mes:HeaderColumnPosition>
                            <mes:ViewColumnPosition>-1</mes:ViewColumnPosition>
                            <mes:ViewRowPosition>-1</mes:ViewRowPosition>
                            <mes:ViewFieldWidth>1</mes:ViewFieldWidth>
                            <mes:ViewFieldHeight>1</mes:ViewFieldHeight>
                            <mes:EditColumnPosition>2</mes:EditColumnPosition>
                            <mes:EditRowPosition>16</mes:EditRowPosition>
                            <mes:EditFieldWidth>1</mes:EditFieldWidth>
                            <mes:EditFieldHeight>1</mes:EditFieldHeight>
                            <mes:JSONConfigText>{}</mes:JSONConfigText>
                        </mes:Details>
                    </mes:PageLayoutField>
                </mes:PageLayoutFields>
                <mes:PageLayoutFilters/>
            </mes:PageLayout>
        </mes:PageLayouts>
        <mes:ReportGroupDatas/>
        <mes:Forms/>
    </mes:Firm>
</mes:LxERP>