<?xml version="1.0" encoding="UTF-8"?>
<mes:LxERP xmlns:mes="http://iwms.lucernex.com/messaging">
    <mes:Firm Name="Selenium-608">
        <mes:PageLayouts>
            <mes:PageLayout>
                <mes:ClientID>SQL152_Test_10_20150929_173954061_28442</mes:ClientID>
                <mes:PageLayoutName>Parcel Location Subpage created</mes:PageLayoutName>
                <mes:Details>
                    <mes:AllowUserCreate>false</mes:AllowUserCreate>
                    <mes:AllowEdit>true</mes:AllowEdit>
                    <mes:IsGlobalReport>true</mes:IsGlobalReport>
                    <mes:OutputType>L</mes:OutputType>
                    <mes:PageLayoutType>V</mes:PageLayoutType>
                    <mes:PrimaryCodeSQLTableID>Parcel</mes:PrimaryCodeSQLTableID>
                    <mes:FirmID>Selenium-608</mes:FirmID>
                    <mes:EntitySelectionFilter>31</mes:EntitySelectionFilter>
                    <mes:RunModeFilters>0</mes:RunModeFilters>
                </mes:Details>
                <mes:PageLayoutFields>
                    <mes:PageLayoutField>
                        <mes:ClientID>SQL152_Test_10_20150929_173954072_1207527</mes:ClientID>
                        <mes:PageLayoutID ClientID="SQL152_Test_10_20150929_173954061_28442">Parcel Location Subpage created</mes:PageLayoutID>
                        <mes:ReportGroupAvailableFieldID ClientID="ERP_510">StaticText</mes:ReportGroupAvailableFieldID>
                        <mes:Details>
                            <mes:FirmID>Selenium-608</mes:FirmID>
                            <mes:StaticText>State / Province</mes:StaticText>
                            <mes:DisplayLabel>State / Province</mes:DisplayLabel>
                            <mes:DisplayOption1>0</mes:DisplayOption1>
                            <mes:DisplayOption2>160</mes:DisplayOption2>
                            <mes:HeaderColumnPosition>-1</mes:HeaderColumnPosition>
                            <mes:ViewColumnPosition>-1</mes:ViewColumnPosition>
                            <mes:ViewRowPosition>-1</mes:ViewRowPosition>
                            <mes:ViewFieldWidth>1</mes:ViewFieldWidth>
                            <mes:ViewFieldHeight>1</mes:ViewFieldHeight>
                            <mes:EditColumnPosition>3</mes:EditColumnPosition>
                            <mes:EditRowPosition>6</mes:EditRowPosition>
                            <mes:EditFieldWidth>1</mes:EditFieldWidth>
                            <mes:EditFieldHeight>1</mes:EditFieldHeight>
                            <mes:JSONConfigText>{}</mes:JSONConfigText>
                        </mes:Details>
                    </mes:PageLayoutField>
                    <mes:PageLayoutField>
                        <mes:ClientID>SQL152_Test_10_20150929_173954080_1207528</mes:ClientID>
                        <mes:PageLayoutID ClientID="SQL152_Test_10_20150929_173954061_28442">Parcel Location Subpage created</mes:PageLayoutID>
                        <mes:ReportGroupAvailableFieldID ClientID="Dev_1686">PostalCode</mes:ReportGroupAvailableFieldID>
                        <mes:Details>
                            <mes:FirmID>Selenium-608</mes:FirmID>
                            <mes:DisplayLabel>Postal Code</mes:DisplayLabel>
                            <mes:DisplayOption1>256</mes:DisplayOption1>
                            <mes:DisplayOption2>0</mes:DisplayOption2>
                            <mes:HeaderColumnPosition>-1</mes:HeaderColumnPosition>
                            <mes:ViewColumnPosition>-1</mes:ViewColumnPosition>
                            <mes:ViewRowPosition>-1</mes:ViewRowPosition>
                            <mes:ViewFieldWidth>1</mes:ViewFieldWidth>
                            <mes:ViewFieldHeight>1</mes:ViewFieldHeight>
                            <mes:EditColumnPosition>2</mes:EditColumnPosition>
                            <mes:EditRowPosition>7</mes:EditRowPosition>
                            <mes:EditFieldWidth>1</mes:EditFieldWidth>
                            <mes:EditFieldHeight>1</mes:EditFieldHeight>
                            <mes:JSONConfigText>{}</mes:JSONConfigText>
                        </mes:Details>
                    </mes:PageLayoutField>
                    <mes:PageLayoutField>
                        <mes:ClientID>SQL152_Test_10_20150929_173954090_1207529</mes:ClientID>
                        <mes:PageLayoutID ClientID="SQL152_Test_10_20150929_173954061_28442">Parcel Location Subpage created</mes:PageLayoutID>
                        <mes:ReportGroupAvailableFieldID ClientID="Dev_1687">IStateProvinceCountryID</mes:ReportGroupAvailableFieldID>
                        <mes:Details>
                            <mes:FirmID>Selenium-608</mes:FirmID>
                            <mes:DisplayLabel>State Province Country</mes:DisplayLabel>
                            <mes:DisplayOption1>256</mes:DisplayOption1>
                            <mes:DisplayOption2>0</mes:DisplayOption2>
                            <mes:HeaderColumnPosition>-1</mes:HeaderColumnPosition>
                            <mes:ViewColumnPosition>-1</mes:ViewColumnPosition>
                            <mes:ViewRowPosition>-1</mes:ViewRowPosition>
                            <mes:ViewFieldWidth>1</mes:ViewFieldWidth>
                            <mes:ViewFieldHeight>1</mes:ViewFieldHeight>
                            <mes:EditColumnPosition>4</mes:EditColumnPosition>
                            <mes:EditRowPosition>6</mes:EditRowPosition>
                            <mes:EditFieldWidth>1</mes:EditFieldWidth>
                            <mes:EditFieldHeight>1</mes:EditFieldHeight>
                            <mes:JSONConfigText>{}</mes:JSONConfigText>
                        </mes:Details>
                    </mes:PageLayoutField>
                    <mes:PageLayoutField>
                        <mes:ClientID>SQL152_Test_10_20150929_173954099_1207530</mes:ClientID>
                        <mes:PageLayoutID ClientID="SQL152_Test_10_20150929_173954061_28442">Parcel Location Subpage created</mes:PageLayoutID>
                        <mes:ReportGroupAvailableFieldID ClientID="Dev_1689">StreetAddress1</mes:ReportGroupAvailableFieldID>
                        <mes:Details>
                            <mes:FirmID>Selenium-608</mes:FirmID>
                            <mes:DisplayLabel>Street Address #1</mes:DisplayLabel>
                            <mes:DisplayOption1>256</mes:DisplayOption1>
                            <mes:DisplayOption2>0</mes:DisplayOption2>
                            <mes:HeaderColumnPosition>-1</mes:HeaderColumnPosition>
                            <mes:ViewColumnPosition>-1</mes:ViewColumnPosition>
                            <mes:ViewRowPosition>-1</mes:ViewRowPosition>
                            <mes:ViewFieldWidth>1</mes:ViewFieldWidth>
                            <mes:ViewFieldHeight>1</mes:ViewFieldHeight>
                            <mes:EditColumnPosition>2</mes:EditColumnPosition>
                            <mes:EditRowPosition>2</mes:EditRowPosition>
                            <mes:EditFieldWidth>3</mes:EditFieldWidth>
                            <mes:EditFieldHeight>1</mes:EditFieldHeight>
                            <mes:JSONConfigText>{}</mes:JSONConfigText>
                        </mes:Details>
                    </mes:PageLayoutField>
                    <mes:PageLayoutField>
                        <mes:ClientID>SQL152_Test_10_20150929_173954110_1207531</mes:ClientID>
                        <mes:PageLayoutID ClientID="SQL152_Test_10_20150929_173954061_28442">Parcel Location Subpage created</mes:PageLayoutID>
                        <mes:ReportGroupAvailableFieldID ClientID="Dev_1690">StreetAddress2</mes:ReportGroupAvailableFieldID>
                        <mes:Details>
                            <mes:FirmID>Selenium-608</mes:FirmID>
                            <mes:DisplayLabel>Street Address #2</mes:DisplayLabel>
                            <mes:DisplayOption1>256</mes:DisplayOption1>
                            <mes:DisplayOption2>0</mes:DisplayOption2>
                            <mes:HeaderColumnPosition>-1</mes:HeaderColumnPosition>
                            <mes:ViewColumnPosition>-1</mes:ViewColumnPosition>
                            <mes:ViewRowPosition>-1</mes:ViewRowPosition>
                            <mes:ViewFieldWidth>1</mes:ViewFieldWidth>
                            <mes:ViewFieldHeight>1</mes:ViewFieldHeight>
                            <mes:EditColumnPosition>2</mes:EditColumnPosition>
                            <mes:EditRowPosition>3</mes:EditRowPosition>
                            <mes:EditFieldWidth>3</mes:EditFieldWidth>
                            <mes:EditFieldHeight>1</mes:EditFieldHeight>
                            <mes:JSONConfigText>{}</mes:JSONConfigText>
                        </mes:Details>
                    </mes:PageLayoutField>
                    <mes:PageLayoutField>
                        <mes:ClientID>SQL152_Test_10_20150929_173954121_1207532</mes:ClientID>
                        <mes:PageLayoutID ClientID="SQL152_Test_10_20150929_173954061_28442">Parcel Location Subpage created</mes:PageLayoutID>
                        <mes:ReportGroupAvailableFieldID ClientID="ERP_510">StaticText</mes:ReportGroupAvailableFieldID>
                        <mes:Details>
                            <mes:FirmID>Selenium-608</mes:FirmID>
                            <mes:StaticText>Address</mes:StaticText>
                            <mes:DisplayLabel>Address</mes:DisplayLabel>
                            <mes:DisplayOption1>0</mes:DisplayOption1>
                            <mes:DisplayOption2>160</mes:DisplayOption2>
                            <mes:HeaderColumnPosition>-1</mes:HeaderColumnPosition>
                            <mes:ViewColumnPosition>-1</mes:ViewColumnPosition>
                            <mes:ViewRowPosition>-1</mes:ViewRowPosition>
                            <mes:ViewFieldWidth>1</mes:ViewFieldWidth>
                            <mes:ViewFieldHeight>1</mes:ViewFieldHeight>
                            <mes:EditColumnPosition>1</mes:EditColumnPosition>
                            <mes:EditRowPosition>2</mes:EditRowPosition>
                            <mes:EditFieldWidth>1</mes:EditFieldWidth>
                            <mes:EditFieldHeight>1</mes:EditFieldHeight>
                            <mes:JSONConfigText>{}</mes:JSONConfigText>
                        </mes:Details>
                    </mes:PageLayoutField>
                    <mes:PageLayoutField>
                        <mes:ClientID>SQL152_Test_10_20150929_173954133_1207533</mes:ClientID>
                        <mes:PageLayoutID ClientID="SQL152_Test_10_20150929_173954061_28442">Parcel Location Subpage created</mes:PageLayoutID>
                        <mes:ReportGroupAvailableFieldID ClientID="ERP_510">StaticText</mes:ReportGroupAvailableFieldID>
                        <mes:Details>
                            <mes:FirmID>Selenium-608</mes:FirmID>
                            <mes:StaticText>Zip / Postal Code</mes:StaticText>
                            <mes:DisplayLabel>Zip / Postal Code</mes:DisplayLabel>
                            <mes:DisplayOption1>0</mes:DisplayOption1>
                            <mes:DisplayOption2>160</mes:DisplayOption2>
                            <mes:HeaderColumnPosition>-1</mes:HeaderColumnPosition>
                            <mes:ViewColumnPosition>-1</mes:ViewColumnPosition>
                            <mes:ViewRowPosition>-1</mes:ViewRowPosition>
                            <mes:ViewFieldWidth>1</mes:ViewFieldWidth>
                            <mes:ViewFieldHeight>1</mes:ViewFieldHeight>
                            <mes:EditColumnPosition>1</mes:EditColumnPosition>
                            <mes:EditRowPosition>7</mes:EditRowPosition>
                            <mes:EditFieldWidth>1</mes:EditFieldWidth>
                            <mes:EditFieldHeight>1</mes:EditFieldHeight>
                            <mes:JSONConfigText>{}</mes:JSONConfigText>
                        </mes:Details>
                    </mes:PageLayoutField>
                    <mes:PageLayoutField>
                        <mes:ClientID>SQL152_Test_10_20150929_173954142_1207534</mes:ClientID>
                        <mes:PageLayoutID ClientID="SQL152_Test_10_20150929_173954061_28442">Parcel Location Subpage created</mes:PageLayoutID>
                        <mes:ReportGroupAvailableFieldID ClientID="Dev_1691">StreetAddress3</mes:ReportGroupAvailableFieldID>
                        <mes:Details>
                            <mes:FirmID>Selenium-608</mes:FirmID>
                            <mes:DisplayLabel>Street Address #3</mes:DisplayLabel>
                            <mes:DisplayOption1>256</mes:DisplayOption1>
                            <mes:DisplayOption2>0</mes:DisplayOption2>
                            <mes:HeaderColumnPosition>-1</mes:HeaderColumnPosition>
                            <mes:ViewColumnPosition>-1</mes:ViewColumnPosition>
                            <mes:ViewRowPosition>-1</mes:ViewRowPosition>
                            <mes:ViewFieldWidth>1</mes:ViewFieldWidth>
                            <mes:ViewFieldHeight>1</mes:ViewFieldHeight>
                            <mes:EditColumnPosition>2</mes:EditColumnPosition>
                            <mes:EditRowPosition>4</mes:EditRowPosition>
                            <mes:EditFieldWidth>3</mes:EditFieldWidth>
                            <mes:EditFieldHeight>1</mes:EditFieldHeight>
                            <mes:JSONConfigText>{}</mes:JSONConfigText>
                        </mes:Details>
                    </mes:PageLayoutField>
                    <mes:PageLayoutField>
                        <mes:ClientID>SQL152_Test_10_20150929_173954153_1207535</mes:ClientID>
                        <mes:PageLayoutID ClientID="SQL152_Test_10_20150929_173954061_28442">Parcel Location Subpage created</mes:PageLayoutID>
                        <mes:ReportGroupAvailableFieldID ClientID="ERP_510">StaticText</mes:ReportGroupAvailableFieldID>
                        <mes:Details>
                            <mes:FirmID>Selenium-608</mes:FirmID>
                            <mes:StaticText>City</mes:StaticText>
                            <mes:DisplayLabel>City</mes:DisplayLabel>
                            <mes:DisplayOption1>0</mes:DisplayOption1>
                            <mes:DisplayOption2>160</mes:DisplayOption2>
                            <mes:HeaderColumnPosition>-1</mes:HeaderColumnPosition>
                            <mes:ViewColumnPosition>-1</mes:ViewColumnPosition>
                            <mes:ViewRowPosition>-1</mes:ViewRowPosition>
                            <mes:ViewFieldWidth>1</mes:ViewFieldWidth>
                            <mes:ViewFieldHeight>1</mes:ViewFieldHeight>
                            <mes:EditColumnPosition>1</mes:EditColumnPosition>
                            <mes:EditRowPosition>6</mes:EditRowPosition>
                            <mes:EditFieldWidth>1</mes:EditFieldWidth>
                            <mes:EditFieldHeight>1</mes:EditFieldHeight>
                            <mes:JSONConfigText>{}</mes:JSONConfigText>
                        </mes:Details>
                    </mes:PageLayoutField>
                    <mes:PageLayoutField>
                        <mes:ClientID>SQL152_Test_10_20150929_173954164_1207536</mes:ClientID>
                        <mes:PageLayoutID ClientID="SQL152_Test_10_20150929_173954061_28442">Parcel Location Subpage created</mes:PageLayoutID>
                        <mes:ReportGroupAvailableFieldID ClientID="Dev_1682">City</mes:ReportGroupAvailableFieldID>
                        <mes:Details>
                            <mes:FirmID>Selenium-608</mes:FirmID>
                            <mes:DisplayLabel>City</mes:DisplayLabel>
                            <mes:DisplayOption1>256</mes:DisplayOption1>
                            <mes:DisplayOption2>0</mes:DisplayOption2>
                            <mes:HeaderColumnPosition>-1</mes:HeaderColumnPosition>
                            <mes:ViewColumnPosition>-1</mes:ViewColumnPosition>
                            <mes:ViewRowPosition>-1</mes:ViewRowPosition>
                            <mes:ViewFieldWidth>1</mes:ViewFieldWidth>
                            <mes:ViewFieldHeight>1</mes:ViewFieldHeight>
                            <mes:EditColumnPosition>2</mes:EditColumnPosition>
                            <mes:EditRowPosition>6</mes:EditRowPosition>
                            <mes:EditFieldWidth>1</mes:EditFieldWidth>
                            <mes:EditFieldHeight>1</mes:EditFieldHeight>
                            <mes:JSONConfigText>{}</mes:JSONConfigText>
                        </mes:Details>
                    </mes:PageLayoutField>
                    <mes:PageLayoutField>
                        <mes:ClientID>SQL152_Test_10_20150929_173954175_1207537</mes:ClientID>
                        <mes:PageLayoutID ClientID="SQL152_Test_10_20150929_173954061_28442">Parcel Location Subpage created</mes:PageLayoutID>
                        <mes:ReportGroupAvailableFieldID ClientID="Dev_1692">StreetAddress4</mes:ReportGroupAvailableFieldID>
                        <mes:Details>
                            <mes:FirmID>Selenium-608</mes:FirmID>
                            <mes:DisplayLabel>Street Address #4</mes:DisplayLabel>
                            <mes:DisplayOption1>256</mes:DisplayOption1>
                            <mes:DisplayOption2>0</mes:DisplayOption2>
                            <mes:HeaderColumnPosition>-1</mes:HeaderColumnPosition>
                            <mes:ViewColumnPosition>-1</mes:ViewColumnPosition>
                            <mes:ViewRowPosition>-1</mes:ViewRowPosition>
                            <mes:ViewFieldWidth>1</mes:ViewFieldWidth>
                            <mes:ViewFieldHeight>1</mes:ViewFieldHeight>
                            <mes:EditColumnPosition>2</mes:EditColumnPosition>
                            <mes:EditRowPosition>5</mes:EditRowPosition>
                            <mes:EditFieldWidth>3</mes:EditFieldWidth>
                            <mes:EditFieldHeight>1</mes:EditFieldHeight>
                            <mes:JSONConfigText>{}</mes:JSONConfigText>
                        </mes:Details>
                    </mes:PageLayoutField>
                    <mes:PageLayoutField>
                        <mes:ClientID>SQL152_Test_10_20150929_173954185_1207538</mes:ClientID>
                        <mes:PageLayoutID ClientID="SQL152_Test_10_20150929_173954061_28442">Parcel Location Subpage created</mes:PageLayoutID>
                        <mes:ReportGroupAvailableFieldID ClientID="Dev_1683">CountryID</mes:ReportGroupAvailableFieldID>
                        <mes:Details>
                            <mes:FirmID>Selenium-608</mes:FirmID>
                            <mes:DisplayLabel>Country</mes:DisplayLabel>
                            <mes:DisplayOption1>256</mes:DisplayOption1>
                            <mes:DisplayOption2>0</mes:DisplayOption2>
                            <mes:HeaderColumnPosition>-1</mes:HeaderColumnPosition>
                            <mes:ViewColumnPosition>-1</mes:ViewColumnPosition>
                            <mes:ViewRowPosition>-1</mes:ViewRowPosition>
                            <mes:ViewFieldWidth>1</mes:ViewFieldWidth>
                            <mes:ViewFieldHeight>1</mes:ViewFieldHeight>
                            <mes:EditColumnPosition>4</mes:EditColumnPosition>
                            <mes:EditRowPosition>7</mes:EditRowPosition>
                            <mes:EditFieldWidth>1</mes:EditFieldWidth>
                            <mes:EditFieldHeight>1</mes:EditFieldHeight>
                            <mes:JSONConfigText>{}</mes:JSONConfigText>
                        </mes:Details>
                    </mes:PageLayoutField>
                    <mes:PageLayoutField>
                        <mes:ClientID>SQL152_Test_10_20150929_173954196_1207539</mes:ClientID>
                        <mes:PageLayoutID ClientID="SQL152_Test_10_20150929_173954061_28442">Parcel Location Subpage created</mes:PageLayoutID>
                        <mes:ReportGroupAvailableFieldID ClientID="ERP_510">StaticText</mes:ReportGroupAvailableFieldID>
                        <mes:Details>
                            <mes:FirmID>Selenium-608</mes:FirmID>
                            <mes:StaticText>Country</mes:StaticText>
                            <mes:DisplayLabel>Country</mes:DisplayLabel>
                            <mes:DisplayOption1>0</mes:DisplayOption1>
                            <mes:DisplayOption2>160</mes:DisplayOption2>
                            <mes:HeaderColumnPosition>-1</mes:HeaderColumnPosition>
                            <mes:ViewColumnPosition>-1</mes:ViewColumnPosition>
                            <mes:ViewRowPosition>-1</mes:ViewRowPosition>
                            <mes:ViewFieldWidth>1</mes:ViewFieldWidth>
                            <mes:ViewFieldHeight>1</mes:ViewFieldHeight>
                            <mes:EditColumnPosition>3</mes:EditColumnPosition>
                            <mes:EditRowPosition>7</mes:EditRowPosition>
                            <mes:EditFieldWidth>1</mes:EditFieldWidth>
                            <mes:EditFieldHeight>1</mes:EditFieldHeight>
                            <mes:JSONConfigText>{}</mes:JSONConfigText>
                        </mes:Details>
                    </mes:PageLayoutField>
                    <mes:PageLayoutField>
                        <mes:ClientID>SQL152_Test_10_20150929_173954206_1207540</mes:ClientID>
                        <mes:PageLayoutID ClientID="SQL152_Test_10_20150929_173954061_28442">Parcel Location Subpage created</mes:PageLayoutID>
                        <mes:ReportGroupAvailableFieldID ClientID="ERP_508">BlankRow</mes:ReportGroupAvailableFieldID>
                        <mes:Details>
                            <mes:FirmID>Selenium-608</mes:FirmID>
                            <mes:DisplayLabel>Blank Row</mes:DisplayLabel>
                            <mes:DisplayOption1>0</mes:DisplayOption1>
                            <mes:DisplayOption2>0</mes:DisplayOption2>
                            <mes:HeaderColumnPosition>-1</mes:HeaderColumnPosition>
                            <mes:ViewColumnPosition>-1</mes:ViewColumnPosition>
                            <mes:ViewRowPosition>-1</mes:ViewRowPosition>
                            <mes:ViewFieldWidth>1</mes:ViewFieldWidth>
                            <mes:ViewFieldHeight>1</mes:ViewFieldHeight>
                            <mes:EditColumnPosition>1</mes:EditColumnPosition>
                            <mes:EditRowPosition>8</mes:EditRowPosition>
                            <mes:EditFieldWidth>1</mes:EditFieldWidth>
                            <mes:EditFieldHeight>1</mes:EditFieldHeight>
                            <mes:JSONConfigText>{}</mes:JSONConfigText>
                        </mes:Details>
                    </mes:PageLayoutField>
                    <mes:PageLayoutField>
                        <mes:ClientID>SQL152_Test_10_20150929_173954216_1207541</mes:ClientID>
                        <mes:PageLayoutID ClientID="SQL152_Test_10_20150929_173954061_28442">Parcel Location Subpage created</mes:PageLayoutID>
                        <mes:ReportGroupAvailableFieldID ClientID="MORTVM_Dev_7.0.3_20101122_191028025_0">CrossStreet1</mes:ReportGroupAvailableFieldID>
                        <mes:Details>
                            <mes:FirmID>Selenium-608</mes:FirmID>
                            <mes:DisplayLabel>Cross Street #1</mes:DisplayLabel>
                            <mes:DisplayOption1>268435712</mes:DisplayOption1>
                            <mes:DisplayOption2>0</mes:DisplayOption2>
                            <mes:HeaderColumnPosition>-1</mes:HeaderColumnPosition>
                            <mes:ViewColumnPosition>-1</mes:ViewColumnPosition>
                            <mes:ViewRowPosition>-1</mes:ViewRowPosition>
                            <mes:ViewFieldWidth>1</mes:ViewFieldWidth>
                            <mes:ViewFieldHeight>1</mes:ViewFieldHeight>
                            <mes:EditColumnPosition>2</mes:EditColumnPosition>
                            <mes:EditRowPosition>9</mes:EditRowPosition>
                            <mes:EditFieldWidth>1</mes:EditFieldWidth>
                            <mes:EditFieldHeight>1</mes:EditFieldHeight>
                            <mes:JSONConfigText>{}</mes:JSONConfigText>
                        </mes:Details>
                    </mes:PageLayoutField>
                    <mes:PageLayoutField>
                        <mes:ClientID>SQL152_Test_10_20150929_173954227_1207542</mes:ClientID>
                        <mes:PageLayoutID ClientID="SQL152_Test_10_20150929_173954061_28442">Parcel Location Subpage created</mes:PageLayoutID>
                        <mes:ReportGroupAvailableFieldID ClientID="ERP_510">StaticText</mes:ReportGroupAvailableFieldID>
                        <mes:Details>
                            <mes:FirmID>Selenium-608</mes:FirmID>
                            <mes:StaticText>Cross Street#1</mes:StaticText>
                            <mes:DisplayLabel>Cross Street#1</mes:DisplayLabel>
                            <mes:DisplayOption1>0</mes:DisplayOption1>
                            <mes:DisplayOption2>160</mes:DisplayOption2>
                            <mes:HeaderColumnPosition>-1</mes:HeaderColumnPosition>
                            <mes:ViewColumnPosition>-1</mes:ViewColumnPosition>
                            <mes:ViewRowPosition>-1</mes:ViewRowPosition>
                            <mes:ViewFieldWidth>1</mes:ViewFieldWidth>
                            <mes:ViewFieldHeight>1</mes:ViewFieldHeight>
                            <mes:EditColumnPosition>1</mes:EditColumnPosition>
                            <mes:EditRowPosition>9</mes:EditRowPosition>
                            <mes:EditFieldWidth>1</mes:EditFieldWidth>
                            <mes:EditFieldHeight>1</mes:EditFieldHeight>
                            <mes:JSONConfigText>{}</mes:JSONConfigText>
                        </mes:Details>
                    </mes:PageLayoutField>
                    <mes:PageLayoutField>
                        <mes:ClientID>SQL152_Test_10_20150929_173954243_1207543</mes:ClientID>
                        <mes:PageLayoutID ClientID="SQL152_Test_10_20150929_173954061_28442">Parcel Location Subpage created</mes:PageLayoutID>
                        <mes:ReportGroupAvailableFieldID ClientID="MORTVM_Dev_7.0.3_20101122_191028026_1">CrossStreet2</mes:ReportGroupAvailableFieldID>
                        <mes:Details>
                            <mes:FirmID>Selenium-608</mes:FirmID>
                            <mes:DisplayLabel>Cross Street #2</mes:DisplayLabel>
                            <mes:DisplayOption1>268435712</mes:DisplayOption1>
                            <mes:DisplayOption2>0</mes:DisplayOption2>
                            <mes:HeaderColumnPosition>-1</mes:HeaderColumnPosition>
                            <mes:ViewColumnPosition>-1</mes:ViewColumnPosition>
                            <mes:ViewRowPosition>-1</mes:ViewRowPosition>
                            <mes:ViewFieldWidth>1</mes:ViewFieldWidth>
                            <mes:ViewFieldHeight>1</mes:ViewFieldHeight>
                            <mes:EditColumnPosition>4</mes:EditColumnPosition>
                            <mes:EditRowPosition>9</mes:EditRowPosition>
                            <mes:EditFieldWidth>1</mes:EditFieldWidth>
                            <mes:EditFieldHeight>1</mes:EditFieldHeight>
                            <mes:JSONConfigText>{}</mes:JSONConfigText>
                        </mes:Details>
                    </mes:PageLayoutField>
                    <mes:PageLayoutField>
                        <mes:ClientID>SQL152_Test_10_20150929_173954253_1207544</mes:ClientID>
                        <mes:PageLayoutID ClientID="SQL152_Test_10_20150929_173954061_28442">Parcel Location Subpage created</mes:PageLayoutID>
                        <mes:ReportGroupAvailableFieldID ClientID="ERP_510">StaticText</mes:ReportGroupAvailableFieldID>
                        <mes:Details>
                            <mes:FirmID>Selenium-608</mes:FirmID>
                            <mes:StaticText>Cross Street#2</mes:StaticText>
                            <mes:DisplayLabel>Cross Street#2</mes:DisplayLabel>
                            <mes:DisplayOption1>0</mes:DisplayOption1>
                            <mes:DisplayOption2>160</mes:DisplayOption2>
                            <mes:HeaderColumnPosition>-1</mes:HeaderColumnPosition>
                            <mes:ViewColumnPosition>-1</mes:ViewColumnPosition>
                            <mes:ViewRowPosition>-1</mes:ViewRowPosition>
                            <mes:ViewFieldWidth>1</mes:ViewFieldWidth>
                            <mes:ViewFieldHeight>1</mes:ViewFieldHeight>
                            <mes:EditColumnPosition>3</mes:EditColumnPosition>
                            <mes:EditRowPosition>9</mes:EditRowPosition>
                            <mes:EditFieldWidth>1</mes:EditFieldWidth>
                            <mes:EditFieldHeight>1</mes:EditFieldHeight>
                            <mes:JSONConfigText>{}</mes:JSONConfigText>
                        </mes:Details>
                    </mes:PageLayoutField>
                    <mes:PageLayoutField>
                        <mes:ClientID>SQL152_Test_10_20150929_173954262_1207545</mes:ClientID>
                        <mes:PageLayoutID ClientID="SQL152_Test_10_20150929_173954061_28442">Parcel Location Subpage created</mes:PageLayoutID>
                        <mes:ReportGroupAvailableFieldID ClientID="LXDFWSEML001_BBTestRM_20091015_171557328_1">UseLocationAddress</mes:ReportGroupAvailableFieldID>
                        <mes:Details>
                            <mes:FirmID>Selenium-608</mes:FirmID>
                            <mes:DisplayLabel>Use Location Address?</mes:DisplayLabel>
                            <mes:DisplayOption1>1032</mes:DisplayOption1>
                            <mes:DisplayOption2>0</mes:DisplayOption2>
                            <mes:HeaderColumnPosition>-1</mes:HeaderColumnPosition>
                            <mes:ViewColumnPosition>-1</mes:ViewColumnPosition>
                            <mes:ViewRowPosition>-1</mes:ViewRowPosition>
                            <mes:ViewFieldWidth>1</mes:ViewFieldWidth>
                            <mes:ViewFieldHeight>1</mes:ViewFieldHeight>
                            <mes:EditColumnPosition>1</mes:EditColumnPosition>
                            <mes:EditRowPosition>1</mes:EditRowPosition>
                            <mes:EditFieldWidth>1</mes:EditFieldWidth>
                            <mes:EditFieldHeight>1</mes:EditFieldHeight>
                            <mes:JSONConfigText>{}</mes:JSONConfigText>
                        </mes:Details>
                    </mes:PageLayoutField>
                </mes:PageLayoutFields>
                <mes:PageLayoutFilters/>
            </mes:PageLayout>
        </mes:PageLayouts>
        <mes:ReportGroupDatas/>
        <mes:Forms/>
    </mes:Firm>
</mes:LxERP>